[
{
"original": {
"src": "https://images.pexels.com/photos/189349/pexels-photo-189349.jpeg",
"width": 5760,
"height": 3840
},
"large2x": {
"src": "https://images.pexels.com/photos/189349/pexels-photo-189349.jpeg?auto=compress&cs=tinysrgb&dpr=2&h=650&w=940",
"width": 940,
"height": 650
},
"large": {
"src": "https://images.pexels.com/photos/189349/pexels-photo-189349.jpeg?auto=compress&cs=tinysrgb&h=650&w=940",
"width": 940,
"height": 650
},
"portrait": {
"src": "https://images.pexels.com/photos/189349/pexels-photo-189349.jpeg?auto=compress&cs=tinysrgb&fit=crop&h=1200&w=800",
"width": 800,
"height": 1200
},
"landscape": {
"src": "https://images.pexels.com/photos/189349/pexels-photo-189349.jpeg?auto=compress&cs=tinysrgb&fit=crop&h=1200&w=800",
"width": 1200,
"height": 627
},
"tiny": {
"src": "https://images.pexels.com/photos/189349/pexels-photo-189349.jpeg?auto=compress&cs=tinysrgb&fit=crop&h=1200&w=800",
"width": 280,
"height": 200
},
"blurHash": "|~LfjXRQbHbaaebIayfka}~AaLWXbHayfkf6fkjuxtn$f6ayfQazfQfQf6OFoeo0ayj[ayfkfQfPNdbaayo0fkjZfRfPj?n+bHa{fQf7fQf7a|a|s.WCj[bHjZfkjZjtfRkCn%azfkaya}fPfQfRS4oLjZfQfjfQfQf6fQ"
},
{
"original": {
"src": "https://images.pexels.com/photos/1001682/pexels-photo-1001682.jpeg",
"width": 3888,
"height": 2592
},
"large2x": {
"src": "https://images.pexels.com/photos/1001682/pexels-photo-1001682.jpeg?auto=compress&cs=tinysrgb&dpr=2&h=650&w=940",
"width": 940,
"height": 650
},
"large": {
"src": "https://images.pexels.com/photos/1001682/pexels-photo-1001682.jpeg?auto=compress&cs=tinysrgb&h=650&w=940",
"width": 940,
"height": 650
},
"portrait": {
"src": "https://images.pexels.com/photos/1001682/pexels-photo-1001682.jpeg?auto=compress&cs=tinysrgb&fit=crop&h=1200&w=800",
"width": 800,
"height": 1200
},
"landscape": {
"src": "https://images.pexels.com/photos/1001682/pexels-photo-1001682.jpeg?auto=compress&cs=tinysrgb&fit=crop&h=1200&w=800",
"width": 1200,
"height": 627
},
"tiny": {
"src": "https://images.pexels.com/photos/1001682/pexels-photo-1001682.jpeg?auto=compress&cs=tinysrgb&fit=crop&h=1200&w=800",
"width": 280,
"height": 200
},
"blurHash": "|$I5[BRjj[ayfQfkfQayfQ~pkCayfQfQfQfQfQfQ%2fQj[fkfkayfQj[fQS5bHf6ayfQfQfQayfQE2fkfQfPayj[ayj[fQNHayfQj[fQayfkfQfQs:azayayfQayfQfQfQs:fQazfQa|j[ayfQfQt6jtj[j[fQayfQa|fQ"
},
{
"original": {
"src": "https://images.pexels.com/photos/847393/pexels-photo-847393.jpeg",
"width": 4000,
"height": 3000
},
"large2x": {
"src": "https://images.pexels.com/photos/847393/pexels-photo-847393.jpeg?auto=compress&cs=tinysrgb&dpr=2&h=650&w=940",
"width": 940,
"height": 650
},
"large": {
"src": "https://images.pexels.com/photos/847393/pexels-photo-847393.jpeg?auto=compress&cs=tinysrgb&h=650&w=940",
"width": 940,
"height": 650
},
"portrait": {
"src": "https://images.pexels.com/photos/847393/pexels-photo-847393.jpeg?auto=compress&cs=tinysrgb&fit=crop&h=1200&w=800",
"width": 800,
"height": 1200
},
"landscape": {
"src": "https://images.pexels.com/photos/847393/pexels-photo-847393.jpeg?auto=compress&cs=tinysrgb&fit=crop&h=1200&w=800",
"width": 1200,
"height": 627
},
"tiny": {
"src": "https://images.pexels.com/photos/847393/pexels-photo-847393.jpeg?auto=compress&cs=tinysrgb&fit=crop&h=1200&w=800",
"width": 280,
"height": 200
},
"blurHash": "|B6^Ca*{s,NKRkWBoyjbf8yDv}njX8W;aff6kCkCL}JDkWn5t6f*kCaKjZMbKPW=rrsoe.azofjYVuaeocfSoeaekVWBj]x^r=ocSOW=jZaLbHWCt,o{VtV[kCafo|aej[MxR.g2jFoLkVWDj?jZR5RQjbo|jYV[ayaLae"
},
{
"original": {
"src": "https://images.pexels.com/photos/1802268/pexels-photo-1802268.jpeg",
"width": 3879,
"height": 5818
},
"large2x": {
"src": "https://images.pexels.com/photos/1802268/pexels-photo-1802268.jpeg?auto=compress&cs=tinysrgb&dpr=2&h=650&w=940",
"width": 940,
"height": 650
},
"large": {
"src": "https://images.pexels.com/photos/1802268/pexels-photo-1802268.jpeg?auto=compress&cs=tinysrgb&h=650&w=940",
"width": 940,
"height": 650
},
"portrait": {
"src": "https://images.pexels.com/photos/1802268/pexels-photo-1802268.jpeg?auto=compress&cs=tinysrgb&fit=crop&h=1200&w=800",
"width": 800,
"height": 1200
},
"landscape": {
"src": "https://images.pexels.com/photos/1802268/pexels-photo-1802268.jpeg?auto=compress&cs=tinysrgb&fit=crop&h=1200&w=800",
"width": 1200,
"height": 627
},
"tiny": {
"src": "https://images.pexels.com/photos/1802268/pexels-photo-1802268.jpeg?auto=compress&cs=tinysrgb&fit=crop&h=1200&w=800",
"width": 280,
"height": 200
},
"blurHash": "|pFG8:X9R+ayj[fkayj[fQ~pkWR*ayjZj[ayf6fQxvozWVayfQj[fQj[fQIqoJj[axj[f6jtj[fQIVj[kCayjsfQfRfQjtofWBj[ayj@a}a|fkj@%2R%ofazj[ayfkayjsxuWBj@j]jZfkayfkfPW=WBoJj[ayj[j@ayj["
},
{
"original": {
"src": "https://images.pexels.com/photos/561463/pexels-photo-561463.jpeg",
"width": 3269,
"height": 4810
},
"large2x": {
"src": "https://images.pexels.com/photos/561463/pexels-photo-561463.jpeg?auto=compress&cs=tinysrgb&dpr=2&h=650&w=940",
"width": 940,
"height": 650
},
"large": {
"src": "https://images.pexels.com/photos/561463/pexels-photo-561463.jpeg?auto=compress&cs=tinysrgb&h=650&w=940",
"width": 940,
"height": 650
},
"portrait": {
"src": "https://images.pexels.com/photos/561463/pexels-photo-561463.jpeg?auto=compress&cs=tinysrgb&fit=crop&h=1200&w=800",
"width": 800,
"height": 1200
},
"landscape": {
"src": "https://images.pexels.com/photos/561463/pexels-photo-561463.jpeg?auto=compress&cs=tinysrgb&fit=crop&h=1200&w=800",
"width": 1200,
"height": 627
},
"tiny": {
"src": "https://images.pexels.com/photos/561463/pexels-photo-561463.jpeg?auto=compress&cs=tinysrgb&fit=crop&h=1200&w=800",
"width": 280,
"height": 200
},
"blurHash": "|oH0q$s.R*WBWBbHbHj[fk^joLWCjZjZjsazfRa|BUjGj@f+fka|ayayjZ1gazj@kBj[j[jsf6f6NabHjZayf6ayj[j[ju,;bajZjFe.f6bHbHfkw]bHayjZjZfQa|a|a|NHjGj[bafkfjf6jZf6NbjGbHbbbHfjjZjZfQ"
},
{
"original": {
"src": "https://images.pexels.com/photos/1533720/pexels-photo-1533720.jpeg",
"width": 6000,
"height": 4000
},
"large2x": {
"src": "https://images.pexels.com/photos/1533720/pexels-photo-1533720.jpeg?auto=compress&cs=tinysrgb&dpr=2&h=650&w=940",
"width": 940,
"height": 650
},
"large": {
"src": "https://images.pexels.com/photos/1533720/pexels-photo-1533720.jpeg?auto=compress&cs=tinysrgb&h=650&w=940",
"width": 940,
"height": 650
},
"portrait": {
"src": "https://images.pexels.com/photos/1533720/pexels-photo-1533720.jpeg?auto=compress&cs=tinysrgb&fit=crop&h=1200&w=800",
"width": 800,
"height": 1200
},
"landscape": {
"src": "https://images.pexels.com/photos/1533720/pexels-photo-1533720.jpeg?auto=compress&cs=tinysrgb&fit=crop&h=1200&w=800",
"width": 1200,
"height": 627
},
"tiny": {
"src": "https://images.pexels.com/photos/1533720/pexels-photo-1533720.jpeg?auto=compress&cs=tinysrgb&fit=crop&h=1200&w=800",
"width": 280,
"height": 200
},
"blurHash": "|yI5[CRjfkayayfkfkayay~qbHayazfQfQfQfQfQkCoej[jtj[ayfQj[fQIpf6jsj[fQj[f6fQf6M|flfRayayj[j[ayfks:WBfkayfkayfkfQfQxafQayj[fQfkayj[ayWBoef6j[j[f7fQfQfQR+jtofayfQj[j[f6j["
},
{
"original": {
"src": "https://images.pexels.com/photos/37403/bora-bora-french-polynesia-sunset-ocean.jpg",
"width": 7020,
"height": 3163
},
"large2x": {
"src": "https://images.pexels.com/photos/37403/bora-bora-french-polynesia-sunset-ocean.jpg?auto=compress&cs=tinysrgb&dpr=2&h=650&w=940",
"width": 940,
"height": 650
},
"large": {
"src": "https://images.pexels.com/photos/37403/bora-bora-french-polynesia-sunset-ocean.jpg?auto=compress&cs=tinysrgb&h=650&w=940",
"width": 940,
"height": 650
},
"portrait": {
"src": "https://images.pexels.com/photos/37403/bora-bora-french-polynesia-sunset-ocean.jpg?auto=compress&cs=tinysrgb&fit=crop&h=1200&w=800",
"width": 800,
"height": 1200
},
"landscape": {
"src": "https://images.pexels.com/photos/37403/bora-bora-french-polynesia-sunset-ocean.jpg?auto=compress&cs=tinysrgb&fit=crop&h=1200&w=800",
"width": 1200,
"height": 627
},
"tiny": {
"src": "https://images.pexels.com/photos/37403/bora-bora-french-polynesia-sunset-ocean.jpg?auto=compress&cs=tinysrgb&fit=crop&h=1200&w=800",
"width": 280,
"height": 200
},
"blurHash": "|SFQ2w-NNyoej]WBWCWCay9EWCn$WVa{oej?oej@0oRjn#jufjjuoLj@ayRQR-j@j[WBa#ayayj[,SSiWYoJjZj[fPWBayrqxtWBafkCWBWBj[kB9Hs-j?a~oeofoej[j[o}Rjj[fkayayj[fkae-:WBt6oLWBfkfPayae"
},
{
"original": {
"src": "https://images.pexels.com/photos/756856/pexels-photo-756856.jpeg",
"width": 1836,
"height": 2291
},
"large2x": {
"src": "https://images.pexels.com/photos/756856/pexels-photo-756856.jpeg?auto=compress&cs=tinysrgb&dpr=2&h=650&w=940",
"width": 940,
"height": 650
},
"large": {
"src": "https://images.pexels.com/photos/756856/pexels-photo-756856.jpeg?auto=compress&cs=tinysrgb&h=650&w=940",
"width": 940,
"height": 650
},
"portrait": {
"src": "https://images.pexels.com/photos/756856/pexels-photo-756856.jpeg?auto=compress&cs=tinysrgb&fit=crop&h=1200&w=800",
"width": 800,
"height": 1200
},
"landscape": {
"src": "https://images.pexels.com/photos/756856/pexels-photo-756856.jpeg?auto=compress&cs=tinysrgb&fit=crop&h=1200&w=800",
"width": 1200,
"height": 627
},
"tiny": {
"src": "https://images.pexels.com/photos/756856/pexels-photo-756856.jpeg?auto=compress&cs=tinysrgb&fit=crop&h=1200&w=800",
"width": 280,
"height": 200
},
"blurHash": "|hHM1J00RjV@oft7WBa}of%MM{M|xut7WVjZRjjt%MWXWCt7Rjayj[WBj[R*ofofRjofazofj[ayR*j]t7WBWVj[a|ayayR*RjxtbHayj[WBofofRjayt7ofRjWBayofj[WBayjsj[a}j[j[j[j[ofj[ayayofWBf6WBay"
},
{
"original": {
"src": "https://images.pexels.com/photos/2860705/pexels-photo-2860705.jpeg",
"width": 4000,
"height": 6000
},
"large2x": {
"src": "https://images.pexels.com/photos/2860705/pexels-photo-2860705.jpeg?auto=compress&cs=tinysrgb&dpr=2&h=650&w=940",
"width": 940,
"height": 650
},
"large": {
"src": "https://images.pexels.com/photos/2860705/pexels-photo-2860705.jpeg?auto=compress&cs=tinysrgb&h=650&w=940",
"width": 940,
"height": 650
},
"portrait": {
"src": "https://images.pexels.com/photos/2860705/pexels-photo-2860705.jpeg?auto=compress&cs=tinysrgb&fit=crop&h=1200&w=800",
"width": 800,
"height": 1200
},
"landscape": {
"src": "https://images.pexels.com/photos/2860705/pexels-photo-2860705.jpeg?auto=compress&cs=tinysrgb&fit=crop&h=1200&w=800",
"width": 1200,
"height": 627
},
"tiny": {
"src": "https://images.pexels.com/photos/2860705/pexels-photo-2860705.jpeg?auto=compress&cs=tinysrgb&fit=crop&h=1200&w=800",
"width": 280,
"height": 200
},
"blurHash": "|GBh$dVYQR%gRjo#ayoLf+.8IAnhtlW=WCWBaeWBMyi^tmMxt7aefQWVj]e8o}SOV@s:RPt7ayayyYR5V?tRkDofj[WWWBV@ozxuWVRiogWAofj[V@oLX8bbofV?kCofa{V?ogRPofofWBofV@ozRjj[oeozoJoeofayoL"
},
{
"original": {
"src": "https://images.pexels.com/photos/994605/pexels-photo-994605.jpeg",
"width": 2726,
"height": 2047
},
"large2x": {
"src": "https://images.pexels.com/photos/994605/pexels-photo-994605.jpeg?auto=compress&cs=tinysrgb&dpr=2&h=650&w=940",
"width": 940,
"height": 650
},
"large": {
"src": "https://images.pexels.com/photos/994605/pexels-photo-994605.jpeg?auto=compress&cs=tinysrgb&h=650&w=940",
"width": 940,
"height": 650
},
"portrait": {
"src": "https://images.pexels.com/photos/994605/pexels-photo-994605.jpeg?auto=compress&cs=tinysrgb&fit=crop&h=1200&w=800",
"width": 800,
"height": 1200
},
"landscape": {
"src": "https://images.pexels.com/photos/994605/pexels-photo-994605.jpeg?auto=compress&cs=tinysrgb&fit=crop&h=1200&w=800",
"width": 1200,
"height": 627
},
"tiny": {
"src": "https://images.pexels.com/photos/994605/pexels-photo-994605.jpeg?auto=compress&cs=tinysrgb&fit=crop&h=1200&w=800",
"width": 280,
"height": 200
},
"blurHash": "|bI~DNozs-ofoLs:oej[j[B=o#%1ayayjuWCf6j[01Iof+j[R*oLWVfRfQ$fNGR*oeWCt6j[oej[-pR*ozWBWBWVWBayfQ-oM{oLWXj[ayayWWazE1s.s:ayoLofoefPoL%2WBoLayR*ayWBWVfPxZR*WBs:j[oeoeoLa}"
},
{
"original": {
"src": "https://images.pexels.com/photos/1076758/pexels-photo-1076758.jpeg",
"width": 3230,
"height": 3648
},
"large2x": {
"src": "https://images.pexels.com/photos/1076758/pexels-photo-1076758.jpeg?auto=compress&cs=tinysrgb&dpr=2&h=650&w=940",
"width": 940,
"height": 650
},
"large": {
"src": "https://images.pexels.com/photos/1076758/pexels-photo-1076758.jpeg?auto=compress&cs=tinysrgb&h=650&w=940",
"width": 940,
"height": 650
},
"portrait": {
"src": "https://images.pexels.com/photos/1076758/pexels-photo-1076758.jpeg?auto=compress&cs=tinysrgb&fit=crop&h=1200&w=800",
"width": 800,
"height": 1200
},
"landscape": {
"src": "https://images.pexels.com/photos/1076758/pexels-photo-1076758.jpeg?auto=compress&cs=tinysrgb&fit=crop&h=1200&w=800",
"width": 1200,
"height": 627
},
"tiny": {
"src": "https://images.pexels.com/photos/1076758/pexels-photo-1076758.jpeg?auto=compress&cs=tinysrgb&fit=crop&h=1200&w=800",
"width": 280,
"height": 200
},
"blurHash": "|SBryVJ.9a$eofozWCV@kW~VT0EMr=tQoKWCWUj[%}xFNHNdxZn%WBkCaet8v}R*T0rrbbayofaeo}r?WCXSjEWqofo2WonOkDn%jFS#aeoMj?azwcX8oKn$SNn%j[jZj[s9S4kCs9R*j]fjaeofn%WVj]oJWBbIoJaeof"
},
{
"original": {
"src": "https://images.pexels.com/photos/1452701/pexels-photo-1452701.jpeg",
"width": 5472,
"height": 3072
},
"large2x": {
"src": "https://images.pexels.com/photos/1452701/pexels-photo-1452701.jpeg?auto=compress&cs=tinysrgb&dpr=2&h=650&w=940",
"width": 940,
"height": 650
},
"large": {
"src": "https://images.pexels.com/photos/1452701/pexels-photo-1452701.jpeg?auto=compress&cs=tinysrgb&h=650&w=940",
"width": 940,
"height": 650
},
"portrait": {
"src": "https://images.pexels.com/photos/1452701/pexels-photo-1452701.jpeg?auto=compress&cs=tinysrgb&fit=crop&h=1200&w=800",
"width": 800,
"height": 1200
},
"landscape": {
"src": "https://images.pexels.com/photos/1452701/pexels-photo-1452701.jpeg?auto=compress&cs=tinysrgb&fit=crop&h=1200&w=800",
"width": 1200,
"height": 627
},
"tiny": {
"src": "https://images.pexels.com/photos/1452701/pexels-photo-1452701.jpeg?auto=compress&cs=tinysrgb&fit=crop&h=1200&w=800",
"width": 280,
"height": 200
},
"blurHash": "|M8F[p%#WBa}jsofj[bHay.mx[ozoyofkCazj[fQxaoLozozj[ayayf6j[tRofa|fQa}fkj[jtf6oLjsayj[kCkCj[ayayofkCf6fkfQjsfkaya|ofofaeayayf6j[j[j[ofofaxayayf6j[fQfkjZkCfPayayfQfQa|j["
},
{
"original": {
"src": "https://images.pexels.com/photos/812958/pexels-photo-812958.jpeg",
"width": 5184,
"height": 3456
},
"large2x": {
"src": "https://images.pexels.com/photos/812958/pexels-photo-812958.jpeg?auto=compress&cs=tinysrgb&dpr=2&h=650&w=940",
"width": 940,
"height": 650
},
"large": {
"src": "https://images.pexels.com/photos/812958/pexels-photo-812958.jpeg?auto=compress&cs=tinysrgb&h=650&w=940",
"width": 940,
"height": 650
},
"portrait": {
"src": "https://images.pexels.com/photos/812958/pexels-photo-812958.jpeg?auto=compress&cs=tinysrgb&fit=crop&h=1200&w=800",
"width": 800,
"height": 1200
},
"landscape": {
"src": "https://images.pexels.com/photos/812958/pexels-photo-812958.jpeg?auto=compress&cs=tinysrgb&fit=crop&h=1200&w=800",
"width": 1200,
"height": 627
},
"tiny": {
"src": "https://images.pexels.com/photos/812958/pexels-photo-812958.jpeg?auto=compress&cs=tinysrgb&fit=crop&h=1200&w=800",
"width": 280,
"height": 200
},
"blurHash": "|BI=os9F?v%gj@9FbHt7t7VXM{?bn~RjIVofIVM{4T-;?bD%bFoeWXjuaz4.?b-;9Ft7kCxuRkxtM{%2n$W=-;ayxtWBaz9F%MR+%MxuM{M{ofxu%MM{WBxuRjadayM{Rk_3IUxa%MRjRjWBWVoe%MWBWARj%2S2xut6WB"
},
{
"original": {
"src": "https://images.pexels.com/photos/457881/pexels-photo-457881.jpeg",
"width": 3936,
"height": 2624
},
"large2x": {
"src": "https://images.pexels.com/photos/457881/pexels-photo-457881.jpeg?auto=compress&cs=tinysrgb&dpr=2&h=650&w=940",
"width": 940,
"height": 650
},
"large": {
"src": "https://images.pexels.com/photos/457881/pexels-photo-457881.jpeg?auto=compress&cs=tinysrgb&h=650&w=940",
"width": 940,
"height": 650
},
"portrait": {
"src": "https://images.pexels.com/photos/457881/pexels-photo-457881.jpeg?auto=compress&cs=tinysrgb&fit=crop&h=1200&w=800",
"width": 800,
"height": 1200
},
"landscape": {
"src": "https://images.pexels.com/photos/457881/pexels-photo-457881.jpeg?auto=compress&cs=tinysrgb&fit=crop&h=1200&w=800",
"width": 1200,
"height": 627
},
"tiny": {
"src": "https://images.pexels.com/photos/457881/pexels-photo-457881.jpeg?auto=compress&cs=tinysrgb&fit=crop&h=1200&w=800",
"width": 280,
"height": 200
},
"blurHash": "|rG1Y?NIoefkj?a}fQfQfQ0BWEoeazjtfQfQazfQ-Mayj[azfQfjfQayjtO8oda#ayfQj[a|fQfQRooeazjsfQj[azfQj[s:a|j[j?azj[ayfQfQouWCoLaya}j[ayfQfQoJWCoLazj[fQayfQfQoLfPj@ayj[azf6fQfQ"
},
{
"original": {
"src": "https://images.pexels.com/photos/1350197/pexels-photo-1350197.jpeg",
"width": 2835,
"height": 1877
},
"large2x": {
"src": "https://images.pexels.com/photos/1350197/pexels-photo-1350197.jpeg?auto=compress&cs=tinysrgb&dpr=2&h=650&w=940",
"width": 940,
"height": 650
},
"large": {
"src": "https://images.pexels.com/photos/1350197/pexels-photo-1350197.jpeg?auto=compress&cs=tinysrgb&h=650&w=940",
"width": 940,
"height": 650
},
"portrait": {
"src": "https://images.pexels.com/photos/1350197/pexels-photo-1350197.jpeg?auto=compress&cs=tinysrgb&fit=crop&h=1200&w=800",
"width": 800,
"height": 1200
},
"landscape": {
"src": "https://images.pexels.com/photos/1350197/pexels-photo-1350197.jpeg?auto=compress&cs=tinysrgb&fit=crop&h=1200&w=800",
"width": 1200,
"height": 627
},
"tiny": {
"src": "https://images.pexels.com/photos/1350197/pexels-photo-1350197.jpeg?auto=compress&cs=tinysrgb&fit=crop&h=1200&w=800",
"width": 280,
"height": 200
},
"blurHash": "|Y1%N}kqaKayayfkfQfjf6Z2e.j[f6fjayayf6fkcsaef6j[f6ayf6fQfPeof6adf6fQj[j[fQf6kXfkf6ayfkj[jtfQfkb^bHf7j[j[f6fQfQf6Z$aefjf6fRfRfRfQf6k9j[azaefkj[jtj[fkiwj[fkayf6f6ayfPj["
},
{
"original": {
"src": "https://images.pexels.com/photos/1646311/pexels-photo-1646311.jpeg",
"width": 5184,
"height": 3456
},
"large2x": {
"src": "https://images.pexels.com/photos/1646311/pexels-photo-1646311.jpeg?auto=compress&cs=tinysrgb&dpr=2&h=650&w=940",
"width": 940,
"height": 650
},
"large": {
"src": "https://images.pexels.com/photos/1646311/pexels-photo-1646311.jpeg?auto=compress&cs=tinysrgb&h=650&w=940",
"width": 940,
"height": 650
},
"portrait": {
"src": "https://images.pexels.com/photos/1646311/pexels-photo-1646311.jpeg?auto=compress&cs=tinysrgb&fit=crop&h=1200&w=800",
"width": 800,
"height": 1200
},
"landscape": {
"src": "https://images.pexels.com/photos/1646311/pexels-photo-1646311.jpeg?auto=compress&cs=tinysrgb&fit=crop&h=1200&w=800",
"width": 1200,
"height": 627
},
"tiny": {
"src": "https://images.pexels.com/photos/1646311/pexels-photo-1646311.jpeg?auto=compress&cs=tinysrgb&fit=crop&h=1200&w=800",
"width": 280,
"height": 200
},
"blurHash": "|6BXTQ$+xaShNGxvI9xut7%gozR*RPt7j[xuoLjs8_x]ozn%%MIURjRjWB8wITIA?w-;x]IURjWXtRMxD$s;ozxvozWBt7%hxukCxuRjRjxuWUofDiRjIAM{bHRPxbxuxuRiM{V@RjofNFWBofj[Riayx]M{WBWBoLogWA"
},
{
"original": {
"src": "https://images.pexels.com/photos/3894157/pexels-photo-3894157.jpeg",
"width": 2160,
"height": 3840
},
"large2x": {
"src": "https://images.pexels.com/photos/3894157/pexels-photo-3894157.jpeg?auto=compress&cs=tinysrgb&dpr=2&h=650&w=940",
"width": 940,
"height": 650
},
"large": {
"src": "https://images.pexels.com/photos/3894157/pexels-photo-3894157.jpeg?auto=compress&cs=tinysrgb&h=650&w=940",
"width": 940,
"height": 650
},
"portrait": {
"src": "https://images.pexels.com/photos/3894157/pexels-photo-3894157.jpeg?auto=compress&cs=tinysrgb&fit=crop&h=1200&w=800",
"width": 800,
"height": 1200
},
"landscape": {
"src": "https://images.pexels.com/photos/3894157/pexels-photo-3894157.jpeg?auto=compress&cs=tinysrgb&fit=crop&h=1200&w=800",
"width": 1200,
"height": 627
},
"tiny": {
"src": "https://images.pexels.com/photos/3894157/pexels-photo-3894157.jpeg?auto=compress&cs=tinysrgb&fit=crop&h=1200&w=800",
"width": 280,
"height": 200
},
"blurHash": "|87WjS.mHqRPNKMcRPivxa?w.SozXTR.MwW?kXofVEyDx^WBbwMxMwadoKVsnhs+tRWAROR*jEo#o#VYe.oeRPtlt7WXoKxuo}RkRPtRnhV?jFtRVsjrWVWCs9WVkXtRj[R+bHo#ayadbIj?kCWBaeaKjskDRPkWjYWXoz"
},
{
"original": {
"src": "https://images.pexels.com/photos/1078981/pexels-photo-1078981.jpeg",
"width": 1896,
"height": 2654
},
"large2x": {
"src": "https://images.pexels.com/photos/1078981/pexels-photo-1078981.jpeg?auto=compress&cs=tinysrgb&dpr=2&h=650&w=940",
"width": 940,
"height": 650
},
"large": {
"src": "https://images.pexels.com/photos/1078981/pexels-photo-1078981.jpeg?auto=compress&cs=tinysrgb&h=650&w=940",
"width": 940,
"height": 650
},
"portrait": {
"src": "https://images.pexels.com/photos/1078981/pexels-photo-1078981.jpeg?auto=compress&cs=tinysrgb&fit=crop&h=1200&w=800",
"width": 800,
"height": 1200
},
"landscape": {
"src": "https://images.pexels.com/photos/1078981/pexels-photo-1078981.jpeg?auto=compress&cs=tinysrgb&fit=crop&h=1200&w=800",
"width": 1200,
"height": 627
},
"tiny": {
"src": "https://images.pexels.com/photos/1078981/pexels-photo-1078981.jpeg?auto=compress&cs=tinysrgb&fit=crop&h=1200&w=800",
"width": 280,
"height": 200
},
"blurHash": "|tED*EWCnif7kCayayjbja0zoeaeaya|j[jZaeay=JbabHf6jtayfQj[j[J8bGkCjuayj[a|fkayV@jZa|ayj[ayj[fjj[s;j[ayj[fkjsfQjufRR%WBf7ayfQjaf6fQfjs;kCj[ayf6ayf6a{a|e.aeayj[fkfkfkfQfQ"
},
{
"original": {
"src": "https://images.pexels.com/photos/7321/sea-water-ocean-horizon.jpg",
"width": 3696,
"height": 2455
},
"large2x": {
"src": "https://images.pexels.com/photos/7321/sea-water-ocean-horizon.jpg?auto=compress&cs=tinysrgb&dpr=2&h=650&w=940",
"width": 940,
"height": 650
},
"large": {
"src": "https://images.pexels.com/photos/7321/sea-water-ocean-horizon.jpg?auto=compress&cs=tinysrgb&h=650&w=940",
"width": 940,
"height": 650
},
"portrait": {
"src": "https://images.pexels.com/photos/7321/sea-water-ocean-horizon.jpg?auto=compress&cs=tinysrgb&fit=crop&h=1200&w=800",
"width": 800,
"height": 1200
},
"landscape": {
"src": "https://images.pexels.com/photos/7321/sea-water-ocean-horizon.jpg?auto=compress&cs=tinysrgb&fit=crop&h=1200&w=800",
"width": 1200,
"height": 627
},
"tiny": {
"src": "https://images.pexels.com/photos/7321/sea-water-ocean-horizon.jpg?auto=compress&cs=tinysrgb&fit=crop&h=1200&w=800",
"width": 280,
"height": 200
},
"blurHash": "|hDUGgozayj[jtfkfQfRjtyZj[ayjtfQfQfQfQfQ9Gayj[fQfQfQfQfQa|Rkazj?azfQjtfQfQfQs,ayj@azfQj@fQfQfQfkazj@fQj@fQfQfQfQWBj?a#j@fQa|jtfQfQoLj@azj@fQa|fQfQfQj?azfQfQazfQfQfQfQ"
},
{
"original": {
"src": "https://images.pexels.com/photos/64219/dolphin-marine-mammals-water-sea-64219.jpeg",
"width": 2352,
"height": 1568
},
"large2x": {
"src": "https://images.pexels.com/photos/64219/dolphin-marine-mammals-water-sea-64219.jpeg?auto=compress&cs=tinysrgb&dpr=2&h=650&w=940",
"width": 940,
"height": 650
},
"large": {
"src": "https://images.pexels.com/photos/64219/dolphin-marine-mammals-water-sea-64219.jpeg?auto=compress&cs=tinysrgb&h=650&w=940",
"width": 940,
"height": 650
},
"portrait": {
"src": "https://images.pexels.com/photos/64219/dolphin-marine-mammals-water-sea-64219.jpeg?auto=compress&cs=tinysrgb&fit=crop&h=1200&w=800",
"width": 800,
"height": 1200
},
"landscape": {
"src": "https://images.pexels.com/photos/64219/dolphin-marine-mammals-water-sea-64219.jpeg?auto=compress&cs=tinysrgb&fit=crop&h=1200&w=800",
"width": 1200,
"height": 627
},
"tiny": {
"src": "https://images.pexels.com/photos/64219/dolphin-marine-mammals-water-sea-64219.jpeg?auto=compress&cs=tinysrgb&fit=crop&h=1200&w=800",
"width": 280,
"height": 200
},
"blurHash": "|O7hd:t+MdRORQjEagjZofyZroXoSjbHbwj[kDofS6n,jDXAocV?kWocWBTfXUs.n#j^oHaeayWBTLS%n~s+aKoejEWBkARPWBoeskoea#kBWBa#V?V@afn$oeWXazfka#i^jrbHf+oKbIWEj[j]t7oeWBWBj[aeWEj?oe"
},
{
"original": {
"src": "https://images.pexels.com/photos/1655166/pexels-photo-1655166.jpeg",
"width": 3968,
"height": 2645
},
"large2x": {
"src": "https://images.pexels.com/photos/1655166/pexels-photo-1655166.jpeg?auto=compress&cs=tinysrgb&dpr=2&h=650&w=940",
"width": 940,
"height": 650
},
"large": {
"src": "https://images.pexels.com/photos/1655166/pexels-photo-1655166.jpeg?auto=compress&cs=tinysrgb&h=650&w=940",
"width": 940,
"height": 650
},
"portrait": {
"src": "https://images.pexels.com/photos/1655166/pexels-photo-1655166.jpeg?auto=compress&cs=tinysrgb&fit=crop&h=1200&w=800",
"width": 800,
"height": 1200
},
"landscape": {
"src": "https://images.pexels.com/photos/1655166/pexels-photo-1655166.jpeg?auto=compress&cs=tinysrgb&fit=crop&h=1200&w=800",
"width": 1200,
"height": 627
},
"tiny": {
"src": "https://images.pexels.com/photos/1655166/pexels-photo-1655166.jpeg?auto=compress&cs=tinysrgb&fit=crop&h=1200&w=800",
"width": 280,
"height": 200
},
"blurHash": "|62ljCY$t2o|W.t6WBf*ofTut+bEkWoKWBoLf*bGpGawodW;oLWBj[jZWVnhkVbbozR+spWBbHofo|g2ozWVofV[j[j[WVR*oyWBaejZWBj[j@ayt7R*oLjZV@oLWCbHofWBofWVayjZWBkCfjayayf6j[WVoeW:kCj[WV"
},
{
"original": {
"src": "https://images.pexels.com/photos/462162/pexels-photo-462162.jpeg",
"width": 2000,
"height": 1123
},
"large2x": {
"src": "https://images.pexels.com/photos/462162/pexels-photo-462162.jpeg?auto=compress&cs=tinysrgb&dpr=2&h=650&w=940",
"width": 940,
"height": 650
},
"large": {
"src": "https://images.pexels.com/photos/462162/pexels-photo-462162.jpeg?auto=compress&cs=tinysrgb&h=650&w=940",
"width": 940,
"height": 650
},
"portrait": {
"src": "https://images.pexels.com/photos/462162/pexels-photo-462162.jpeg?auto=compress&cs=tinysrgb&fit=crop&h=1200&w=800",
"width": 800,
"height": 1200
},
"landscape": {
"src": "https://images.pexels.com/photos/462162/pexels-photo-462162.jpeg?auto=compress&cs=tinysrgb&fit=crop&h=1200&w=800",
"width": 1200,
"height": 627
},
"tiny": {
"src": "https://images.pexels.com/photos/462162/pexels-photo-462162.jpeg?auto=compress&cs=tinysrgb&fit=crop&h=1200&w=800",
"width": 280,
"height": 200
},
"blurHash": "|dFP1z%MxtkCoej[j[azjt~AaxWVoKazayayjta|^hRjRkWBayj[fRaya|_2t7oLj[j?a|j@a}j@%0WBjtoLfRjta|j[fQivNGWCR*fkj[j[ayazNdazayoKWCayayj[j[ogs:oea}ayayayazfQMyj[kCfjj[azj[ayj["
},
{
"original": {
"src": "https://images.pexels.com/photos/3560168/pexels-photo-3560168.jpeg",
"width": 7426,
"height": 5304
},
"large2x": {
"src": "https://images.pexels.com/photos/3560168/pexels-photo-3560168.jpeg?auto=compress&cs=tinysrgb&dpr=2&h=650&w=940",
"width": 940,
"height": 650
},
"large": {
"src": "https://images.pexels.com/photos/3560168/pexels-photo-3560168.jpeg?auto=compress&cs=tinysrgb&h=650&w=940",
"width": 940,
"height": 650
},
"portrait": {
"src": "https://images.pexels.com/photos/3560168/pexels-photo-3560168.jpeg?auto=compress&cs=tinysrgb&fit=crop&h=1200&w=800",
"width": 800,
"height": 1200
},
"landscape": {
"src": "https://images.pexels.com/photos/3560168/pexels-photo-3560168.jpeg?auto=compress&cs=tinysrgb&fit=crop&h=1200&w=800",
"width": 1200,
"height": 627
},
"tiny": {
"src": "https://images.pexels.com/photos/3560168/pexels-photo-3560168.jpeg?auto=compress&cs=tinysrgb&fit=crop&h=1200&w=800",
"width": 280,
"height": 200
},
"blurHash": "|BA-*Voyx]M{ozofbHWBjstRD%WBRjofWWbIWBWB?^M{ozaextofayWCaeMxoKtRofxtWBa#WBf6M{-;RkM|kCWXWVayay?bxuRjaxt7aeaeWBjsM|IUMxoJt8t7WVayj[xaM{M_%MxvjsRjWCof%NWB%M%MRjRjRkofof"
},
{
"original": {
"src": "https://images.pexels.com/photos/36717/amazing-animal-beautiful-beautifull.jpg",
"width": 1920,
"height": 1195
},
"large2x": {
"src": "https://images.pexels.com/photos/36717/amazing-animal-beautiful-beautifull.jpg?auto=compress&cs=tinysrgb&dpr=2&h=650&w=940",
"width": 940,
"height": 650
},
"large": {
"src": "https://images.pexels.com/photos/36717/amazing-animal-beautiful-beautifull.jpg?auto=compress&cs=tinysrgb&h=650&w=940",
"width": 940,
"height": 650
},
"portrait": {
"src": "https://images.pexels.com/photos/36717/amazing-animal-beautiful-beautifull.jpg?auto=compress&cs=tinysrgb&fit=crop&h=1200&w=800",
"width": 800,
"height": 1200
},
"landscape": {
"src": "https://images.pexels.com/photos/36717/amazing-animal-beautiful-beautifull.jpg?auto=compress&cs=tinysrgb&fit=crop&h=1200&w=800",
"width": 1200,
"height": 627
},
"tiny": {
"src": "https://images.pexels.com/photos/36717/amazing-animal-beautiful-beautifull.jpg?auto=compress&cs=tinysrgb&fit=crop&h=1200&w=800",
"width": 280,
"height": 200
},
"blurHash": "|KC|tOS2JAoLxGa{afjsoeR:j@j=juWVa|fjjtWV5ksoW-o2NaWVj?juR*-TjbWEjtxGWpjGfRoe1aWo$jS2sWo2j[a|o2aiS2Sga|NajuW.a{R+].WVNaoLoeoLWCjskBEyw{xGjto2jasojtoLWEoKW=jtNaWVsofRWC"
},
{
"original": {
"src": "https://images.pexels.com/photos/1298684/pexels-photo-1298684.jpeg",
"width": 7087,
"height": 3986
},
"large2x": {
"src": "https://images.pexels.com/photos/1298684/pexels-photo-1298684.jpeg?auto=compress&cs=tinysrgb&dpr=2&h=650&w=940",
"width": 940,
"height": 650
},
"large": {
"src": "https://images.pexels.com/photos/1298684/pexels-photo-1298684.jpeg?auto=compress&cs=tinysrgb&h=650&w=940",
"width": 940,
"height": 650
},
"portrait": {
"src": "https://images.pexels.com/photos/1298684/pexels-photo-1298684.jpeg?auto=compress&cs=tinysrgb&fit=crop&h=1200&w=800",
"width": 800,
"height": 1200
},
"landscape": {
"src": "https://images.pexels.com/photos/1298684/pexels-photo-1298684.jpeg?auto=compress&cs=tinysrgb&fit=crop&h=1200&w=800",
"width": 1200,
"height": 627
},
"tiny": {
"src": "https://images.pexels.com/photos/1298684/pexels-photo-1298684.jpeg?auto=compress&cs=tinysrgb&fit=crop&h=1200&w=800",
"width": 280,
"height": 200
},
"blurHash": "|mG,IxDhWBWBs:WCbHbHj[~VIoaeflf6ayayaxay^+o}WBoKR+ofayj@ayxaxtW=j?WBaxoLfkay%gt7RjWqt7WCa}azj[s.tRogRjofkCWBf6j[WBoet7WCRjofayjtaybboft6ozRkaeofj[fkjFWBWVs.kCWCj[j[fQ"
},
{
"original": {
"src": "https://images.pexels.com/photos/1074505/pexels-photo-1074505.jpeg",
"width": 4000,
"height": 6000
},
"large2x": {
"src": "https://images.pexels.com/photos/1074505/pexels-photo-1074505.jpeg?auto=compress&cs=tinysrgb&dpr=2&h=650&w=940",
"width": 940,
"height": 650
},
"large": {
"src": "https://images.pexels.com/photos/1074505/pexels-photo-1074505.jpeg?auto=compress&cs=tinysrgb&h=650&w=940",
"width": 940,
"height": 650
},
"portrait": {
"src": "https://images.pexels.com/photos/1074505/pexels-photo-1074505.jpeg?auto=compress&cs=tinysrgb&fit=crop&h=1200&w=800",
"width": 800,
"height": 1200
},
"landscape": {
"src": "https://images.pexels.com/photos/1074505/pexels-photo-1074505.jpeg?auto=compress&cs=tinysrgb&fit=crop&h=1200&w=800",
"width": 1200,
"height": 627
},
"tiny": {
"src": "https://images.pexels.com/photos/1074505/pexels-photo-1074505.jpeg?auto=compress&cs=tinysrgb&fit=crop&h=1200&w=800",
"width": 280,
"height": 200
},
"blurHash": "|C57GbTcnOs.bFf,ayaej@.AMcbwtRWVayf6ayfPvOHqS5o}WBaej[kCf7yYMwR5nja}baayj[j[%$oyV@t7kCbHaefkfksqn$W.tRjYaybHj[axRQVtMxkDjZayj[jsayS#kWMwaeofaeaej[j[kVx^W-f+ofV@WBfQfQ"
},
{
"original": {
"src": "https://images.pexels.com/photos/1556796/pexels-photo-1556796.jpeg",
"width": 2191,
"height": 2923
},
"large2x": {
"src": "https://images.pexels.com/photos/1556796/pexels-photo-1556796.jpeg?auto=compress&cs=tinysrgb&dpr=2&h=650&w=940",
"width": 940,
"height": 650
},
"large": {
"src": "https://images.pexels.com/photos/1556796/pexels-photo-1556796.jpeg?auto=compress&cs=tinysrgb&h=650&w=940",
"width": 940,
"height": 650
},
"portrait": {
"src": "https://images.pexels.com/photos/1556796/pexels-photo-1556796.jpeg?auto=compress&cs=tinysrgb&fit=crop&h=1200&w=800",
"width": 800,
"height": 1200
},
"landscape": {
"src": "https://images.pexels.com/photos/1556796/pexels-photo-1556796.jpeg?auto=compress&cs=tinysrgb&fit=crop&h=1200&w=800",
"width": 1200,
"height": 627
},
"tiny": {
"src": "https://images.pexels.com/photos/1556796/pexels-photo-1556796.jpeg?auto=compress&cs=tinysrgb&fit=crop&h=1200&w=800",
"width": 280,
"height": 200
},
"blurHash": "|E0h1HeoY+krkWZhadgOkWeAgOf,e-f+f+f+e.g3Zhg4kqenadeni_f+aeaKe.kDg3f5f,e.enf+eSg3b^axkCg4aeemj[kDe-bwf,eTf+f,f+e.e-e.f+kWbbadkCf,aee:e:fkfPbaenjZg3bFg4e.f6e.eng3bce.j["
},
{
"original": {
"src": "https://images.pexels.com/photos/66258/staniel-cay-swimming-pig-seagull-fish-66258.jpeg",
"width": 3742,
"height": 2505
},
"large2x": {
"src": "https://images.pexels.com/photos/66258/staniel-cay-swimming-pig-seagull-fish-66258.jpeg?auto=compress&cs=tinysrgb&dpr=2&h=650&w=940",
"width": 940,
"height": 650
},
"large": {
"src": "https://images.pexels.com/photos/66258/staniel-cay-swimming-pig-seagull-fish-66258.jpeg?auto=compress&cs=tinysrgb&h=650&w=940",
"width": 940,
"height": 650
},
"portrait": {
"src": "https://images.pexels.com/photos/66258/staniel-cay-swimming-pig-seagull-fish-66258.jpeg?auto=compress&cs=tinysrgb&fit=crop&h=1200&w=800",
"width": 800,
"height": 1200
},
"landscape": {
"src": "https://images.pexels.com/photos/66258/staniel-cay-swimming-pig-seagull-fish-66258.jpeg?auto=compress&cs=tinysrgb&fit=crop&h=1200&w=800",
"width": 1200,
"height": 627
},
"tiny": {
"src": "https://images.pexels.com/photos/66258/staniel-cay-swimming-pig-seagull-fish-66258.jpeg?auto=compress&cs=tinysrgb&fit=crop&h=1200&w=800",
"width": 280,
"height": 200
},
"blurHash": "|FDCmhnOCRTJ+]tQS#Rjoz_@s;buSgsns.Woa}oLTgk?*{rXOEM|n$t7ayOZTJv}rrS#WCnioJWBzVnjOsOroLs:kCV[jFz:spSiNakVo|ofa#X9w0kXafrXV@S2jFozkWn,kXj?s:r?VtNHbGs.nla}bFgMozn$WBV@aK"
},
{
"original": {
"src": "https://images.pexels.com/photos/635279/pexels-photo-635279.jpeg",
"width": 4274,
"height": 2839
},
"large2x": {
"src": "https://images.pexels.com/photos/635279/pexels-photo-635279.jpeg?auto=compress&cs=tinysrgb&dpr=2&h=650&w=940",
"width": 940,
"height": 650
},
"large": {
"src": "https://images.pexels.com/photos/635279/pexels-photo-635279.jpeg?auto=compress&cs=tinysrgb&h=650&w=940",
"width": 940,
"height": 650
},
"portrait": {
"src": "https://images.pexels.com/photos/635279/pexels-photo-635279.jpeg?auto=compress&cs=tinysrgb&fit=crop&h=1200&w=800",
"width": 800,
"height": 1200
},
"landscape": {
"src": "https://images.pexels.com/photos/635279/pexels-photo-635279.jpeg?auto=compress&cs=tinysrgb&fit=crop&h=1200&w=800",
"width": 1200,
"height": 627
},
"tiny": {
"src": "https://images.pexels.com/photos/635279/pexels-photo-635279.jpeg?auto=compress&cs=tinysrgb&fit=crop&h=1200&w=800",
"width": 280,
"height": 200
},
"blurHash": "|bHeCDxuItRjfhofazWBay.9kCjuoJayWWa}axjs0ibIxZk9jFjGfkWVay4;a$ofj[jZf6a}f6j@nNa|R-f6f*kBayjZa}xuofWEWCbHj[jsoJazOtR+kBj[jZjafkj[fPJDbIkBWVjZo0j[j[azWBWWn%oLbHWVj[jZfk"
},
{
"original": {
"src": "https://images.pexels.com/photos/931018/pexels-photo-931018.jpeg",
"width": 3000,
"height": 4000
},
"large2x": {
"src": "https://images.pexels.com/photos/931018/pexels-photo-931018.jpeg?auto=compress&cs=tinysrgb&dpr=2&h=650&w=940",
"width": 940,
"height": 650
},
"large": {
"src": "https://images.pexels.com/photos/931018/pexels-photo-931018.jpeg?auto=compress&cs=tinysrgb&h=650&w=940",
"width": 940,
"height": 650
},
"portrait": {
"src": "https://images.pexels.com/photos/931018/pexels-photo-931018.jpeg?auto=compress&cs=tinysrgb&fit=crop&h=1200&w=800",
"width": 800,
"height": 1200
},
"landscape": {
"src": "https://images.pexels.com/photos/931018/pexels-photo-931018.jpeg?auto=compress&cs=tinysrgb&fit=crop&h=1200&w=800",
"width": 1200,
"height": 627
},
"tiny": {
"src": "https://images.pexels.com/photos/931018/pexels-photo-931018.jpeg?auto=compress&cs=tinysrgb&fit=crop&h=1200&w=800",
"width": 280,
"height": 200
},
"blurHash": "|B8FGpTaM{RjNGozozoLV@*wi{bvf+WBaeaeofbH00sDs:t7t7V[RjWVofEMX7f5nit6ozW=RjjG?cRPRkNGRjoMj[j[az=|ozf+axRjRjaft6bHM{xaofxuoeR*WVjaaeE1n%jHs:t7oykBWCa|W-Rja#RPn+s:oeWCa}"
},
{
"original": {
"src": "https://images.pexels.com/photos/1556797/pexels-photo-1556797.jpeg",
"width": 2992,
"height": 3992
},
"large2x": {
"src": "https://images.pexels.com/photos/1556797/pexels-photo-1556797.jpeg?auto=compress&cs=tinysrgb&dpr=2&h=650&w=940",
"width": 940,
"height": 650
},
"large": {
"src": "https://images.pexels.com/photos/1556797/pexels-photo-1556797.jpeg?auto=compress&cs=tinysrgb&h=650&w=940",
"width": 940,
"height": 650
},
"portrait": {
"src": "https://images.pexels.com/photos/1556797/pexels-photo-1556797.jpeg?auto=compress&cs=tinysrgb&fit=crop&h=1200&w=800",
"width": 800,
"height": 1200
},
"landscape": {
"src": "https://images.pexels.com/photos/1556797/pexels-photo-1556797.jpeg?auto=compress&cs=tinysrgb&fit=crop&h=1200&w=800",
"width": 1200,
"height": 627
},
"tiny": {
"src": "https://images.pexels.com/photos/1556797/pexels-photo-1556797.jpeg?auto=compress&cs=tinysrgb&fit=crop&h=1200&w=800",
"width": 280,
"height": 200
},
"blurHash": "|fDn9DV?t8WUbHfkjsj[ju_4ozazWVayfkj@fkayRlt7RjWBjtayayayayIoRjjsaykCf6fkayj@j?RjofogWBj[j[juf6t7ofWCofayf6j[j[a}ays:j@WBoLayjtayfRWBaeofa{j[kCWVa}fQj[WBayofayj[a|ayj["
},
{
"original": {
"src": "https://images.pexels.com/photos/63340/pexels-photo-63340.jpeg",
"width": 4000,
"height": 3000
},
"large2x": {
"src": "https://images.pexels.com/photos/63340/pexels-photo-63340.jpeg?auto=compress&cs=tinysrgb&dpr=2&h=650&w=940",
"width": 940,
"height": 650
},
"large": {
"src": "https://images.pexels.com/photos/63340/pexels-photo-63340.jpeg?auto=compress&cs=tinysrgb&h=650&w=940",
"width": 940,
"height": 650
},
"portrait": {
"src": "https://images.pexels.com/photos/63340/pexels-photo-63340.jpeg?auto=compress&cs=tinysrgb&fit=crop&h=1200&w=800",
"width": 800,
"height": 1200
},
"landscape": {
"src": "https://images.pexels.com/photos/63340/pexels-photo-63340.jpeg?auto=compress&cs=tinysrgb&fit=crop&h=1200&w=800",
"width": 1200,
"height": 627
},
"tiny": {
"src": "https://images.pexels.com/photos/63340/pexels-photo-63340.jpeg?auto=compress&cs=tinysrgb&fit=crop&h=1200&w=800",
"width": 280,
"height": 200
},
"blurHash": "|dB7NKaeaya|fQj[ayfkf7Ufj[fkfkfQayj[fQfjMdfjj[f6fQj[ayfQfPR~j[azfkfQayfkfQfkoHayfQayfQj[f7fQf6soj[f6fkfQayfQfQfka$ayfjf6fQj[fQfQf6W:fRf7fkfQfQfQfQfRbEf6fQfQayfQfjfQfQ"
},
{
"original": {
"src": "https://images.pexels.com/photos/26681/pexels-photo-26681.jpg",
"width": 5616,
"height": 3744
},
"large2x": {
"src": "https://images.pexels.com/photos/26681/pexels-photo-26681.jpg?auto=compress&cs=tinysrgb&dpr=2&h=650&w=940",
"width": 940,
"height": 650
},
"large": {
"src": "https://images.pexels.com/photos/26681/pexels-photo-26681.jpg?auto=compress&cs=tinysrgb&h=650&w=940",
"width": 940,
"height": 650
},
"portrait": {
"src": "https://images.pexels.com/photos/26681/pexels-photo-26681.jpg?auto=compress&cs=tinysrgb&fit=crop&h=1200&w=800",
"width": 800,
"height": 1200
},
"landscape": {
"src": "https://images.pexels.com/photos/26681/pexels-photo-26681.jpg?auto=compress&cs=tinysrgb&fit=crop&h=1200&w=800",
"width": 1200,
"height": 627
},
"tiny": {
"src": "https://images.pexels.com/photos/26681/pexels-photo-26681.jpg?auto=compress&cs=tinysrgb&fit=crop&h=1200&w=800",
"width": 280,
"height": 200
},
"blurHash": "||L#;7smWBjZofofWBayj[~Vofofj[WBayofj[ayf5WBayayj[a|ayfkjZIpfkjtj[jsj[f7ayj[bIoefQfQfkayj[j[ayt6ayayayf6j[axfQj[afbHj[j[bHfQj]f7fkWCj[ayayjZayayayayjsayayazj[j[fkj[j["
},
{
"original": {
"src": "https://images.pexels.com/photos/1435752/pexels-photo-1435752.jpeg",
"width": 7952,
"height": 5304
},
"large2x": {
"src": "https://images.pexels.com/photos/1435752/pexels-photo-1435752.jpeg?auto=compress&cs=tinysrgb&dpr=2&h=650&w=940",
"width": 940,
"height": 650
},
"large": {
"src": "https://images.pexels.com/photos/1435752/pexels-photo-1435752.jpeg?auto=compress&cs=tinysrgb&h=650&w=940",
"width": 940,
"height": 650
},
"portrait": {
"src": "https://images.pexels.com/photos/1435752/pexels-photo-1435752.jpeg?auto=compress&cs=tinysrgb&fit=crop&h=1200&w=800",
"width": 800,
"height": 1200
},
"landscape": {
"src": "https://images.pexels.com/photos/1435752/pexels-photo-1435752.jpeg?auto=compress&cs=tinysrgb&fit=crop&h=1200&w=800",
"width": 1200,
"height": 627
},
"tiny": {
"src": "https://images.pexels.com/photos/1435752/pexels-photo-1435752.jpeg?auto=compress&cs=tinysrgb&fit=crop&h=1200&w=800",
"width": 280,
"height": 200
},
"blurHash": "|A3M%?tRi_fiaekCkDkDj]lVWVjZozjZj]fkaybHnifkaef7fkj@j[fPfjoMozozj[aeayj]j]kCVsWBaKkBkCjZjtayayaeozfkfQj[a|j[jZj[e.oMe.ayaxaeayfkfPV@aeayj[ofjZaeaeayaKjZj]aeaef6j[j[jZ"
},
{
"original": {
"src": "https://images.pexels.com/photos/37487/pexels-photo-37487.jpeg",
"width": 5277,
"height": 3518
},
"large2x": {
"src": "https://images.pexels.com/photos/37487/pexels-photo-37487.jpeg?auto=compress&cs=tinysrgb&dpr=2&h=650&w=940",
"width": 940,
"height": 650
},
"large": {
"src": "https://images.pexels.com/photos/37487/pexels-photo-37487.jpeg?auto=compress&cs=tinysrgb&h=650&w=940",
"width": 940,
"height": 650
},
"portrait": {
"src": "https://images.pexels.com/photos/37487/pexels-photo-37487.jpeg?auto=compress&cs=tinysrgb&fit=crop&h=1200&w=800",
"width": 800,
"height": 1200
},
"landscape": {
"src": "https://images.pexels.com/photos/37487/pexels-photo-37487.jpeg?auto=compress&cs=tinysrgb&fit=crop&h=1200&w=800",
"width": 1200,
"height": 627
},
"tiny": {
"src": "https://images.pexels.com/photos/37487/pexels-photo-37487.jpeg?auto=compress&cs=tinysrgb&fit=crop&h=1200&w=800",
"width": 280,
"height": 200
},
"blurHash": "|L1;r7j]fPfkfPfRfPfQfQpfj[fQfkfPfQfQfQfQo~fRfRfQfPfQfQfQfRkDfPfRfkfQfQfPfQfRkCf6f6fQfRf6fRfQfQkCfQfkfQf6f6fRfQfQflfQfkfQf6fPfQfPfQf5f6f6fRfkfRfQfPfQf6f6f6fRflfQfQfPfQ"
},
{
"original": {
"src": "https://images.pexels.com/photos/235990/pexels-photo-235990.jpeg",
"width": 3848,
"height": 2565
},
"large2x": {
"src": "https://images.pexels.com/photos/235990/pexels-photo-235990.jpeg?auto=compress&cs=tinysrgb&dpr=2&h=650&w=940",
"width": 940,
"height": 650
},
"large": {
"src": "https://images.pexels.com/photos/235990/pexels-photo-235990.jpeg?auto=compress&cs=tinysrgb&h=650&w=940",
"width": 940,
"height": 650
},
"portrait": {
"src": "https://images.pexels.com/photos/235990/pexels-photo-235990.jpeg?auto=compress&cs=tinysrgb&fit=crop&h=1200&w=800",
"width": 800,
"height": 1200
},
"landscape": {
"src": "https://images.pexels.com/photos/235990/pexels-photo-235990.jpeg?auto=compress&cs=tinysrgb&fit=crop&h=1200&w=800",
"width": 1200,
"height": 627
},
"tiny": {
"src": "https://images.pexels.com/photos/235990/pexels-photo-235990.jpeg?auto=compress&cs=tinysrgb&fit=crop&h=1200&w=800",
"width": 280,
"height": 200
},
"blurHash": "|PCa0-E4${ItxVW?jEofWBPExaWBt7WBWDoKWVj@-;oeRks-R+t6WCj@j[9uWAt7WBkCWBbHj@WVw]n$WraekCaeofWBoeSQaxofoJa#oKWCoeWVt6s.R*j@WWjZj[ayfkR*WCoeazjsoLWVoLayadj]aya#j@WCoeWVj["
},
{
"original": {
"src": "https://images.pexels.com/photos/386148/pexels-photo-386148.jpeg",
"width": 3992,
"height": 2992
},
"large2x": {
"src": "https://images.pexels.com/photos/386148/pexels-photo-386148.jpeg?auto=compress&cs=tinysrgb&dpr=2&h=650&w=940",
"width": 940,
"height": 650
},
"large": {
"src": "https://images.pexels.com/photos/386148/pexels-photo-386148.jpeg?auto=compress&cs=tinysrgb&h=650&w=940",
"width": 940,
"height": 650
},
"portrait": {
"src": "https://images.pexels.com/photos/386148/pexels-photo-386148.jpeg?auto=compress&cs=tinysrgb&fit=crop&h=1200&w=800",
"width": 800,
"height": 1200
},
"landscape": {
"src": "https://images.pexels.com/photos/386148/pexels-photo-386148.jpeg?auto=compress&cs=tinysrgb&fit=crop&h=1200&w=800",
"width": 1200,
"height": 627
},
"tiny": {
"src": "https://images.pexels.com/photos/386148/pexels-photo-386148.jpeg?auto=compress&cs=tinysrgb&fit=crop&h=1200&w=800",
"width": 280,
"height": 200
},
"blurHash": "|lEWOLWAR*ayayj[ayfQay4me.oLayj[fQjufQfQafj[oLj[fQayj[ayj[xbbHa|jtayayfQfQfQo}ayayayj[j[a|j[ayRjjZjuf6ayj[ayaya|V@j[j[j[fQayj[fQj[t7a{f6fkjta|fQj[j[a|aya|ayayj[ayayay"
},
{
"original": {
"src": "https://images.pexels.com/photos/103567/pexels-photo-103567.jpeg",
"width": 4096,
"height": 2304
},
"large2x": {
"src": "https://images.pexels.com/photos/103567/pexels-photo-103567.jpeg?auto=compress&cs=tinysrgb&dpr=2&h=650&w=940",
"width": 940,
"height": 650
},
"large": {
"src": "https://images.pexels.com/photos/103567/pexels-photo-103567.jpeg?auto=compress&cs=tinysrgb&h=650&w=940",
"width": 940,
"height": 650
},
"portrait": {
"src": "https://images.pexels.com/photos/103567/pexels-photo-103567.jpeg?auto=compress&cs=tinysrgb&fit=crop&h=1200&w=800",
"width": 800,
"height": 1200
},
"landscape": {
"src": "https://images.pexels.com/photos/103567/pexels-photo-103567.jpeg?auto=compress&cs=tinysrgb&fit=crop&h=1200&w=800",
"width": 1200,
"height": 627
},
"tiny": {
"src": "https://images.pexels.com/photos/103567/pexels-photo-103567.jpeg?auto=compress&cs=tinysrgb&fit=crop&h=1200&w=800",
"width": 280,
"height": 200
},
"blurHash": "|wG]{$V@Mxj[WBj[jtj[ay~Wf+Rjj[axj[ayj[ay%2j[t7fka|j[ayfPj[kraexuayj[fRayfQjtRkWVt7ayofayj[ayfkRjayV@f6ofayofayfQV?j[Rjf6fjayofayj[kCj@WBa|WBj[ayj[j[ozfkofj[WBj[WBj[fj"
},
{
"original": {
"src": "https://images.pexels.com/photos/312105/pexels-photo-312105.jpeg",
"width": 8516,
"height": 4779
},
"large2x": {
"src": "https://images.pexels.com/photos/312105/pexels-photo-312105.jpeg?auto=compress&cs=tinysrgb&dpr=2&h=650&w=940",
"width": 940,
"height": 650
},
"large": {
"src": "https://images.pexels.com/photos/312105/pexels-photo-312105.jpeg?auto=compress&cs=tinysrgb&h=650&w=940",
"width": 940,
"height": 650
},
"portrait": {
"src": "https://images.pexels.com/photos/312105/pexels-photo-312105.jpeg?auto=compress&cs=tinysrgb&fit=crop&h=1200&w=800",
"width": 800,
"height": 1200
},
"landscape": {
"src": "https://images.pexels.com/photos/312105/pexels-photo-312105.jpeg?auto=compress&cs=tinysrgb&fit=crop&h=1200&w=800",
"width": 1200,
"height": 627
},
"tiny": {
"src": "https://images.pexels.com/photos/312105/pexels-photo-312105.jpeg?auto=compress&cs=tinysrgb&fit=crop&h=1200&w=800",
"width": 280,
"height": 200
},
"blurHash": "|GDc{=bE_NjEaej@M{MxWAoex[IUoexuf6t7ayfRIoD%Mxt8IUxutRt6t7M{RjRQRjM{M{Rjt7RjNaV@xat7t7ofaekCaxD%xutRWBt7j]Rifkayofayt7Rjt7kCV[WVWBRjxuRjayf5ayaeWBa}ae%gt7RjofWBt7ofj["
},
{
"original": {
"src": "https://images.pexels.com/photos/206359/pexels-photo-206359.jpeg",
"width": 2201,
"height": 1467
},
"large2x": {
"src": "https://images.pexels.com/photos/206359/pexels-photo-206359.jpeg?auto=compress&cs=tinysrgb&dpr=2&h=650&w=940",
"width": 940,
"height": 650
},
"large": {
"src": "https://images.pexels.com/photos/206359/pexels-photo-206359.jpeg?auto=compress&cs=tinysrgb&h=650&w=940",
"width": 940,
"height": 650
},
"portrait": {
"src": "https://images.pexels.com/photos/206359/pexels-photo-206359.jpeg?auto=compress&cs=tinysrgb&fit=crop&h=1200&w=800",
"width": 800,
"height": 1200
},
"landscape": {
"src": "https://images.pexels.com/photos/206359/pexels-photo-206359.jpeg?auto=compress&cs=tinysrgb&fit=crop&h=1200&w=800",
"width": 1200,
"height": 627
},
"tiny": {
"src": "https://images.pexels.com/photos/206359/pexels-photo-206359.jpeg?auto=compress&cs=tinysrgb&fit=crop&h=1200&w=800",
"width": 280,
"height": 200
},
"blurHash": "|BCXwCOvtmOZoJsl$MJ-I:}Ht8$*XSkCf+oLW;j]I,-U-Ct9XTX8X8s:s:by$+W;s:bboLkCj]S30x-WV@oexbozX8W=X9NFNZwyWXs:W=j]kCof,[5kNGr=njX9sobckDSiNbR*e.ayoLj[oKbI6*ITwvNHNZR*WX$gjt"
},
{
"original": {
"src": "https://images.pexels.com/photos/1439226/pexels-photo-1439226.jpeg",
"width": 3644,
"height": 5459
},
"large2x": {
"src": "https://images.pexels.com/photos/1439226/pexels-photo-1439226.jpeg?auto=compress&cs=tinysrgb&dpr=2&h=650&w=940",
"width": 940,
"height": 650
},
"large": {
"src": "https://images.pexels.com/photos/1439226/pexels-photo-1439226.jpeg?auto=compress&cs=tinysrgb&h=650&w=940",
"width": 940,
"height": 650
},
"portrait": {
"src": "https://images.pexels.com/photos/1439226/pexels-photo-1439226.jpeg?auto=compress&cs=tinysrgb&fit=crop&h=1200&w=800",
"width": 800,
"height": 1200
},
"landscape": {
"src": "https://images.pexels.com/photos/1439226/pexels-photo-1439226.jpeg?auto=compress&cs=tinysrgb&fit=crop&h=1200&w=800",
"width": 1200,
"height": 627
},
"tiny": {
"src": "https://images.pexels.com/photos/1439226/pexels-photo-1439226.jpeg?auto=compress&cs=tinysrgb&fit=crop&h=1200&w=800",
"width": 280,
"height": 200
},
"blurHash": "|G43irf5adayf5f6fQazfP%hfRfkazfQj[fQa}ayx^bIayazfQj[fQa}ay%%a}aeayf6f6fQfRjtxvadj[ayfkj[fkfkfPtRaef5ayj[j[fQj[jttSadfkWBjsj[fQj[j[oJWAj]WBkCj]j@j[jtogadayWBkCj[fkj[j["
},
{
"original": {
"src": "https://images.pexels.com/photos/391522/pexels-photo-391522.jpeg",
"width": 3992,
"height": 2992
},
"large2x": {
"src": "https://images.pexels.com/photos/391522/pexels-photo-391522.jpeg?auto=compress&cs=tinysrgb&dpr=2&h=650&w=940",
"width": 940,
"height": 650
},
"large": {
"src": "https://images.pexels.com/photos/391522/pexels-photo-391522.jpeg?auto=compress&cs=tinysrgb&h=650&w=940",
"width": 940,
"height": 650
},
"portrait": {
"src": "https://images.pexels.com/photos/391522/pexels-photo-391522.jpeg?auto=compress&cs=tinysrgb&fit=crop&h=1200&w=800",
"width": 800,
"height": 1200
},
"landscape": {
"src": "https://images.pexels.com/photos/391522/pexels-photo-391522.jpeg?auto=compress&cs=tinysrgb&fit=crop&h=1200&w=800",
"width": 1200,
"height": 627
},
"tiny": {
"src": "https://images.pexels.com/photos/391522/pexels-photo-391522.jpeg?auto=compress&cs=tinysrgb&fit=crop&h=1200&w=800",
"width": 280,
"height": 200
},
"blurHash": "|ICZkl-p4.Io%MRjIos:of.ARjt7WBRjayayofay9vE1xas,ayofa{bHf6-;jFNGRjoLj@WCayfQ-;xaR*M{RjRjofj@j[t8bHM{axt7WBoLoLofIoazs:t7s:j@ofayj[IUs:%2ofRjayofWBjsxuogNGWVoKWVWBfQj@"
},
{
"original": {
"src": "https://images.pexels.com/photos/414320/pexels-photo-414320.jpeg",
"width": 5398,
"height": 3037
},
"large2x": {
"src": "https://images.pexels.com/photos/414320/pexels-photo-414320.jpeg?auto=compress&cs=tinysrgb&dpr=2&h=650&w=940",
"width": 940,
"height": 650
},
"large": {
"src": "https://images.pexels.com/photos/414320/pexels-photo-414320.jpeg?auto=compress&cs=tinysrgb&h=650&w=940",
"width": 940,
"height": 650
},
"portrait": {
"src": "https://images.pexels.com/photos/414320/pexels-photo-414320.jpeg?auto=compress&cs=tinysrgb&fit=crop&h=1200&w=800",
"width": 800,
"height": 1200
},
"landscape": {
"src": "https://images.pexels.com/photos/414320/pexels-photo-414320.jpeg?auto=compress&cs=tinysrgb&fit=crop&h=1200&w=800",
"width": 1200,
"height": 627
},
"tiny": {
"src": "https://images.pexels.com/photos/414320/pexels-photo-414320.jpeg?auto=compress&cs=tinysrgb&fit=crop&h=1200&w=800",
"width": 280,
"height": 200
},
"blurHash": "|NEzZm$jS1WVs:t7aeRjkC4;Iot7oJjZa}WVj[a|D4M{s:j?RjofWBayj[v~j[n%WCoLoLj[ayofbcRPNGa#ayayj[j[WBtRozRjofWBWCf6j]ayt8xufkoeofWBflayj[D*s:adkCt7WBa|j[ayWEt7s:ofWBofofj[WB"
},
{
"original": {
"src": "https://images.pexels.com/photos/1086584/pexels-photo-1086584.jpeg",
"width": 6000,
"height": 4000
},
"large2x": {
"src": "https://images.pexels.com/photos/1086584/pexels-photo-1086584.jpeg?auto=compress&cs=tinysrgb&dpr=2&h=650&w=940",
"width": 940,
"height": 650
},
"large": {
"src": "https://images.pexels.com/photos/1086584/pexels-photo-1086584.jpeg?auto=compress&cs=tinysrgb&h=650&w=940",
"width": 940,
"height": 650
},
"portrait": {
"src": "https://images.pexels.com/photos/1086584/pexels-photo-1086584.jpeg?auto=compress&cs=tinysrgb&fit=crop&h=1200&w=800",
"width": 800,
"height": 1200
},
"landscape": {
"src": "https://images.pexels.com/photos/1086584/pexels-photo-1086584.jpeg?auto=compress&cs=tinysrgb&fit=crop&h=1200&w=800",
"width": 1200,
"height": 627
},
"tiny": {
"src": "https://images.pexels.com/photos/1086584/pexels-photo-1086584.jpeg?auto=compress&cs=tinysrgb&fit=crop&h=1200&w=800",
"width": 280,
"height": 200
},
"blurHash": "|65#9=4ny0EH=gI^ofn-a$RyO5,}WJX2R$s.WUWm4o?aD,xpI;$+WBSKsoo+w7E[s}V|t8R%ogjex}D%-sRYowNEs:oHNY#HXoasI-%3V@bbjKs;E1%MRPxuRjoujbR+s:Xen5S$t8NGt7nnbWR$$+NJotV]t7RiW.s;jd"
},
{
"original": {
"src": "https://images.pexels.com/photos/1722206/pexels-photo-1722206.jpeg",
"width": 7087,
"height": 9449
},
"large2x": {
"src": "https://images.pexels.com/photos/1722206/pexels-photo-1722206.jpeg?auto=compress&cs=tinysrgb&dpr=2&h=650&w=940",
"width": 940,
"height": 650
},
"large": {
"src": "https://images.pexels.com/photos/1722206/pexels-photo-1722206.jpeg?auto=compress&cs=tinysrgb&h=650&w=940",
"width": 940,
"height": 650
},
"portrait": {
"src": "https://images.pexels.com/photos/1722206/pexels-photo-1722206.jpeg?auto=compress&cs=tinysrgb&fit=crop&h=1200&w=800",
"width": 800,
"height": 1200
},
"landscape": {
"src": "https://images.pexels.com/photos/1722206/pexels-photo-1722206.jpeg?auto=compress&cs=tinysrgb&fit=crop&h=1200&w=800",
"width": 1200,
"height": 627
},
"tiny": {
"src": "https://images.pexels.com/photos/1722206/pexels-photo-1722206.jpeg?auto=compress&cs=tinysrgb&fit=crop&h=1200&w=800",
"width": 280,
"height": 200
},
"blurHash": "|98EC~%M4mof?cofIUWBt7M{RjozofRjWUogj[WB00Rj.8RjDiWBxuj[WBogj[Rjayxut7V@kCt7x]ofaexuxuj[jtayayxuayNFWBRjRjkCaeRjV@RjNGazt7axRjkCofRixu%MaeRjofj@ayofNGays:WBRjt7xaaxWB"
},
{
"original": {
"src": "https://images.pexels.com/photos/457882/pexels-photo-457882.jpeg",
"width": 3936,
"height": 2624
},
"large2x": {
"src": "https://images.pexels.com/photos/457882/pexels-photo-457882.jpeg?auto=compress&cs=tinysrgb&dpr=2&h=650&w=940",
"width": 940,
"height": 650
},
"large": {
"src": "https://images.pexels.com/photos/457882/pexels-photo-457882.jpeg?auto=compress&cs=tinysrgb&h=650&w=940",
"width": 940,
"height": 650
},
"portrait": {
"src": "https://images.pexels.com/photos/457882/pexels-photo-457882.jpeg?auto=compress&cs=tinysrgb&fit=crop&h=1200&w=800",
"width": 800,
"height": 1200
},
"landscape": {
"src": "https://images.pexels.com/photos/457882/pexels-photo-457882.jpeg?auto=compress&cs=tinysrgb&fit=crop&h=1200&w=800",
"width": 1200,
"height": 627
},
"tiny": {
"src": "https://images.pexels.com/photos/457882/pexels-photo-457882.jpeg?auto=compress&cs=tinysrgb&fit=crop&h=1200&w=800",
"width": 280,
"height": 200
},
"blurHash": "|rKy1Y$yWBoJoIjsWUayjs0YW-ayfPj?fPj?fPfP$eWYfkj[WXfkj[j[fkotj@ayj@f7j@j[fQjuWBWBWVj?jsjsayayjss:WXazj?j@fjfjj@j?oda#j@fQazazjsj?j@R*ayj?fPayayj@ayayjZWVj[fQazfQf7a#a#"
},
{
"original": {
"src": "https://images.pexels.com/photos/734973/pexels-photo-734973.jpeg",
"width": 6000,
"height": 4000
},
"large2x": {
"src": "https://images.pexels.com/photos/734973/pexels-photo-734973.jpeg?auto=compress&cs=tinysrgb&dpr=2&h=650&w=940",
"width": 940,
"height": 650
},
"large": {
"src": "https://images.pexels.com/photos/734973/pexels-photo-734973.jpeg?auto=compress&cs=tinysrgb&h=650&w=940",
"width": 940,
"height": 650
},
"portrait": {
"src": "https://images.pexels.com/photos/734973/pexels-photo-734973.jpeg?auto=compress&cs=tinysrgb&fit=crop&h=1200&w=800",
"width": 800,
"height": 1200
},
"landscape": {
"src": "https://images.pexels.com/photos/734973/pexels-photo-734973.jpeg?auto=compress&cs=tinysrgb&fit=crop&h=1200&w=800",
"width": 1200,
"height": 627
},
"tiny": {
"src": "https://images.pexels.com/photos/734973/pexels-photo-734973.jpeg?auto=compress&cs=tinysrgb&fit=crop&h=1200&w=800",
"width": 280,
"height": 200
},
"blurHash": "|aD1mPfkaej[ayj[a|f6f6_Naya}j[fQfQfQfQfQnhfPfRayj[f6ayfRfQtRj[a|ayj[fQayf6fQjEjtayj[j[a|fQazayozj[ayj[j[fQayfQf6oLf6ayayj[fQf6fkfQfQaya|fQj[fQj[j[f6ofofj[ayj[ayj[jtfQ"
},
{
"original": {
"src": "https://images.pexels.com/photos/1072842/pexels-photo-1072842.jpeg",
"width": 3456,
"height": 5184
},
"large2x": {
"src": "https://images.pexels.com/photos/1072842/pexels-photo-1072842.jpeg?auto=compress&cs=tinysrgb&dpr=2&h=650&w=940",
"width": 940,
"height": 650
},
"large": {
"src": "https://images.pexels.com/photos/1072842/pexels-photo-1072842.jpeg?auto=compress&cs=tinysrgb&h=650&w=940",
"width": 940,
"height": 650
},
"portrait": {
"src": "https://images.pexels.com/photos/1072842/pexels-photo-1072842.jpeg?auto=compress&cs=tinysrgb&fit=crop&h=1200&w=800",
"width": 800,
"height": 1200
},
"landscape": {
"src": "https://images.pexels.com/photos/1072842/pexels-photo-1072842.jpeg?auto=compress&cs=tinysrgb&fit=crop&h=1200&w=800",
"width": 1200,
"height": 627
},
"tiny": {
"src": "https://images.pexels.com/photos/1072842/pexels-photo-1072842.jpeg?auto=compress&cs=tinysrgb&fit=crop&h=1200&w=800",
"width": 280,
"height": 200
},
"blurHash": "|ZAxlloLIoR*ofWBj[s:jt*0bcofjFayfkayWVfQShWVsoofWVoLa|R*a|xbV@NaWCoLayoLs:jtNxRjkCoLj[WVazj[fQI:Rjs:kCWWoLayR*a|RPjFX8WBjFoLj[oLjZRjj]jtofj[R*a|oLj[RPt7ofWBbGoLf6WBa|"
},
{
"original": {
"src": "https://images.pexels.com/photos/1618606/pexels-photo-1618606.jpeg",
"width": 3648,
"height": 2736
},
"large2x": {
"src": "https://images.pexels.com/photos/1618606/pexels-photo-1618606.jpeg?auto=compress&cs=tinysrgb&dpr=2&h=650&w=940",
"width": 940,
"height": 650
},
"large": {
"src": "https://images.pexels.com/photos/1618606/pexels-photo-1618606.jpeg?auto=compress&cs=tinysrgb&h=650&w=940",
"width": 940,
"height": 650
},
"portrait": {
"src": "https://images.pexels.com/photos/1618606/pexels-photo-1618606.jpeg?auto=compress&cs=tinysrgb&fit=crop&h=1200&w=800",
"width": 800,
"height": 1200
},
"landscape": {
"src": "https://images.pexels.com/photos/1618606/pexels-photo-1618606.jpeg?auto=compress&cs=tinysrgb&fit=crop&h=1200&w=800",
"width": 1200,
"height": 627
},
"tiny": {
"src": "https://images.pexels.com/photos/1618606/pexels-photo-1618606.jpeg?auto=compress&cs=tinysrgb&fit=crop&h=1200&w=800",
"width": 280,
"height": 200
},
"blurHash": "|P7ggJofM$aebcWVjba#aem0bca$jvfRbHfkf8ay9lWExVbHjEn%bFj[kCOIn$ovW-axj[axbGj[-4oIR%kCW=WqjFaea#xnWXa_oLbJWWj]jtWCI;WEn,afnjn%bIj]f6R-ofWGR*j?n$aybHoexas.V[k8axbba{ayjZ"
},
{
"original": {
"src": "https://images.pexels.com/photos/273886/pexels-photo-273886.jpeg",
"width": 3872,
"height": 2592
},
"large2x": {
"src": "https://images.pexels.com/photos/273886/pexels-photo-273886.jpeg?auto=compress&cs=tinysrgb&dpr=2&h=650&w=940",
"width": 940,
"height": 650
},
"large": {
"src": "https://images.pexels.com/photos/273886/pexels-photo-273886.jpeg?auto=compress&cs=tinysrgb&h=650&w=940",
"width": 940,
"height": 650
},
"portrait": {
"src": "https://images.pexels.com/photos/273886/pexels-photo-273886.jpeg?auto=compress&cs=tinysrgb&fit=crop&h=1200&w=800",
"width": 800,
"height": 1200
},
"landscape": {
"src": "https://images.pexels.com/photos/273886/pexels-photo-273886.jpeg?auto=compress&cs=tinysrgb&fit=crop&h=1200&w=800",
"width": 1200,
"height": 627
},
"tiny": {
"src": "https://images.pexels.com/photos/273886/pexels-photo-273886.jpeg?auto=compress&cs=tinysrgb&fit=crop&h=1200&w=800",
"width": 280,
"height": 200
},
"blurHash": "|TLYK9r;i^xWs9s,s-s.s..AR-W=R,WXWCWCWCWB0gR+ofR*j[WCayayaynNs:WCs:j]ofkCf+kCRPofa}offkj[j[a|j[%LWBoJWBaxaxaxjsf6RkWBayWBayayayayayRlt6j[ofoej[oLjtj@n$aya|j[ayj[a|j[j["
},
{
"original": {
"src": "https://images.pexels.com/photos/1330218/pexels-photo-1330218.jpeg",
"width": 3000,
"height": 2000
},
"large2x": {
"src": "https://images.pexels.com/photos/1330218/pexels-photo-1330218.jpeg?auto=compress&cs=tinysrgb&dpr=2&h=650&w=940",
"width": 940,
"height": 650
},
"large": {
"src": "https://images.pexels.com/photos/1330218/pexels-photo-1330218.jpeg?auto=compress&cs=tinysrgb&h=650&w=940",
"width": 940,
"height": 650
},
"portrait": {
"src": "https://images.pexels.com/photos/1330218/pexels-photo-1330218.jpeg?auto=compress&cs=tinysrgb&fit=crop&h=1200&w=800",
"width": 800,
"height": 1200
},
"landscape": {
"src": "https://images.pexels.com/photos/1330218/pexels-photo-1330218.jpeg?auto=compress&cs=tinysrgb&fit=crop&h=1200&w=800",
"width": 1200,
"height": 627
},
"tiny": {
"src": "https://images.pexels.com/photos/1330218/pexels-photo-1330218.jpeg?auto=compress&cs=tinysrgb&fit=crop&h=1200&w=800",
"width": 280,
"height": 200
},
"blurHash": "|wAev[tRV@ayayfQf6ayay%%ofaefQayfQfQfQfQMyWBj[j[j[fQfQfkfkD%WBoffQj[fQfQj@fQM{a#oLayfQfkfQfQfQn#j@ayfQayfQazfQfQxYoKayj[ayf6fQfQfQtQj[ayfkfQfQj@fQfQWXayfPf6j[j[j@fQfQ"
},
{
"original": {
"src": "https://images.pexels.com/photos/4666754/pexels-photo-4666754.jpeg",
"width": 2694,
"height": 4032
},
"large2x": {
"src": "https://images.pexels.com/photos/4666754/pexels-photo-4666754.jpeg?auto=compress&cs=tinysrgb&dpr=2&h=650&w=940",
"width": 940,
"height": 650
},
"large": {
"src": "https://images.pexels.com/photos/4666754/pexels-photo-4666754.jpeg?auto=compress&cs=tinysrgb&h=650&w=940",
"width": 940,
"height": 650
},
"portrait": {
"src": "https://images.pexels.com/photos/4666754/pexels-photo-4666754.jpeg?auto=compress&cs=tinysrgb&fit=crop&h=1200&w=800",
"width": 800,
"height": 1200
},
"landscape": {
"src": "https://images.pexels.com/photos/4666754/pexels-photo-4666754.jpeg?auto=compress&cs=tinysrgb&fit=crop&h=1200&w=800",
"width": 1200,
"height": 627
},
"tiny": {
"src": "https://images.pexels.com/photos/4666754/pexels-photo-4666754.jpeg?auto=compress&cs=tinysrgb&fit=crop&h=1200&w=800",
"width": 280,
"height": 200
},
"blurHash": "|R72UFWEH;xZt8R*oeoLWBxuRiRPtSj[RjofoeWBMbaex_ozV?aej[j@ofIot8xaM_WXt7WBWCofR*t7oJM{f+xaWVR*oJV?j@o#WVaekCj]axf6ofWCWBs:jsR*jZoebIxuWVRjofozWBaxofayoeayWBj?oKazfkj@ay"
},
{
"original": {
"src": "https://images.pexels.com/photos/590178/pexels-photo-590178.jpeg",
"width": 3264,
"height": 2448
},
"large2x": {
"src": "https://images.pexels.com/photos/590178/pexels-photo-590178.jpeg?auto=compress&cs=tinysrgb&dpr=2&h=650&w=940",
"width": 940,
"height": 650
},
"large": {
"src": "https://images.pexels.com/photos/590178/pexels-photo-590178.jpeg?auto=compress&cs=tinysrgb&h=650&w=940",
"width": 940,
"height": 650
},
"portrait": {
"src": "https://images.pexels.com/photos/590178/pexels-photo-590178.jpeg?auto=compress&cs=tinysrgb&fit=crop&h=1200&w=800",
"width": 800,
"height": 1200
},
"landscape": {
"src": "https://images.pexels.com/photos/590178/pexels-photo-590178.jpeg?auto=compress&cs=tinysrgb&fit=crop&h=1200&w=800",
"width": 1200,
"height": 627
},
"tiny": {
"src": "https://images.pexels.com/photos/590178/pexels-photo-590178.jpeg?auto=compress&cs=tinysrgb&fit=crop&h=1200&w=800",
"width": 280,
"height": 200
},
"blurHash": "|TC@~lkVV@WBWBayWBofoeOYjsafj[j[j[ayWBf6}?aebIayaxayWBofj[t8aeWCj[fPj[aeWBayV[a#kBjZj[ayayj[j[%2ayWCf6ayayayWVayNFofj@a}j[j[ayj[f6oMj[WCayj@aefQayaykCoMayayj[j[WBj[fP"
},
{
"original": {
"src": "https://images.pexels.com/photos/2397651/pexels-photo-2397651.jpeg",
"width": 7952,
"height": 5304
},
"large2x": {
"src": "https://images.pexels.com/photos/2397651/pexels-photo-2397651.jpeg?auto=compress&cs=tinysrgb&dpr=2&h=650&w=940",
"width": 940,
"height": 650
},
"large": {
"src": "https://images.pexels.com/photos/2397651/pexels-photo-2397651.jpeg?auto=compress&cs=tinysrgb&h=650&w=940",
"width": 940,
"height": 650
},
"portrait": {
"src": "https://images.pexels.com/photos/2397651/pexels-photo-2397651.jpeg?auto=compress&cs=tinysrgb&fit=crop&h=1200&w=800",
"width": 800,
"height": 1200
},
"landscape": {
"src": "https://images.pexels.com/photos/2397651/pexels-photo-2397651.jpeg?auto=compress&cs=tinysrgb&fit=crop&h=1200&w=800",
"width": 1200,
"height": 627
},
"tiny": {
"src": "https://images.pexels.com/photos/2397651/pexels-photo-2397651.jpeg?auto=compress&cs=tinysrgb&fit=crop&h=1200&w=800",
"width": 280,
"height": 200
},
"blurHash": "|@G,w^M|Rjj@WBj[ayayfk~qR*R+juazf6fkfRf6,nbIbHayfPj[ayj@ayn*oejsayj[fPayjta|kXj@fQj[jsfQfkjtfPoIj[a}j@fQfQfQj[fQaej[jsj[fka|j[f6j[bbjsj[j[ayjtjsj[f6axj[j[f6fQjtj[ayj["
},
{
"original": {
"src": "https://images.pexels.com/photos/355288/pexels-photo-355288.jpeg",
"width": 5106,
"height": 3404
},
"large2x": {
"src": "https://images.pexels.com/photos/355288/pexels-photo-355288.jpeg?auto=compress&cs=tinysrgb&dpr=2&h=650&w=940",
"width": 940,
"height": 650
},
"large": {
"src": "https://images.pexels.com/photos/355288/pexels-photo-355288.jpeg?auto=compress&cs=tinysrgb&h=650&w=940",
"width": 940,
"height": 650
},
"portrait": {
"src": "https://images.pexels.com/photos/355288/pexels-photo-355288.jpeg?auto=compress&cs=tinysrgb&fit=crop&h=1200&w=800",
"width": 800,
"height": 1200
},
"landscape": {
"src": "https://images.pexels.com/photos/355288/pexels-photo-355288.jpeg?auto=compress&cs=tinysrgb&fit=crop&h=1200&w=800",
"width": 1200,
"height": 627
},
"tiny": {
"src": "https://images.pexels.com/photos/355288/pexels-photo-355288.jpeg?auto=compress&cs=tinysrgb&fit=crop&h=1200&w=800",
"width": 280,
"height": 200
},
"blurHash": "|C9R|SbJWVxskCWVfloIWBcu%0t7RkfQn$j[ayWCnMDjIpoJaejYaej[azEoNL%LS6WWt6axj?jsnh-;W;jFslfiWVjYoJ,,ROwajERjf6aeaea}M{ozNKRPnhWYodaej[nhNxWUxYR+a$s.jFWEenskxtXAt6aeflWBay"
},
{
"original": {
"src": "https://images.pexels.com/photos/1456291/pexels-photo-1456291.jpeg",
"width": 5421,
"height": 3619
},
"large2x": {
"src": "https://images.pexels.com/photos/1456291/pexels-photo-1456291.jpeg?auto=compress&cs=tinysrgb&dpr=2&h=650&w=940",
"width": 940,
"height": 650
},
"large": {
"src": "https://images.pexels.com/photos/1456291/pexels-photo-1456291.jpeg?auto=compress&cs=tinysrgb&h=650&w=940",
"width": 940,
"height": 650
},
"portrait": {
"src": "https://images.pexels.com/photos/1456291/pexels-photo-1456291.jpeg?auto=compress&cs=tinysrgb&fit=crop&h=1200&w=800",
"width": 800,
"height": 1200
},
"landscape": {
"src": "https://images.pexels.com/photos/1456291/pexels-photo-1456291.jpeg?auto=compress&cs=tinysrgb&fit=crop&h=1200&w=800",
"width": 1200,
"height": 627
},
"tiny": {
"src": "https://images.pexels.com/photos/1456291/pexels-photo-1456291.jpeg?auto=compress&cs=tinysrgb&fit=crop&h=1200&w=800",
"width": 280,
"height": 200
},
"blurHash": "|LB$M@hjX7oKWVa#aebHaf7}eWi~bcoJj@jFkBf6t+bbena#bbafjta}jZX8kCj[jFf+j?afkCaff+bba}aebIbHe.bHjZbbkBj?jZkCf7j?j[a|fRbIayafa|ayazaykCbHaya#j[j?a}kBjYbbkCjZkBf6j[j?bHaeba"
},
{
"original": {
"src": "https://images.pexels.com/photos/1820041/pexels-photo-1820041.jpeg",
"width": 3072,
"height": 4608
},
"large2x": {
"src": "https://images.pexels.com/photos/1820041/pexels-photo-1820041.jpeg?auto=compress&cs=tinysrgb&dpr=2&h=650&w=940",
"width": 940,
"height": 650
},
"large": {
"src": "https://images.pexels.com/photos/1820041/pexels-photo-1820041.jpeg?auto=compress&cs=tinysrgb&h=650&w=940",
"width": 940,
"height": 650
},
"portrait": {
"src": "https://images.pexels.com/photos/1820041/pexels-photo-1820041.jpeg?auto=compress&cs=tinysrgb&fit=crop&h=1200&w=800",
"width": 800,
"height": 1200
},
"landscape": {
"src": "https://images.pexels.com/photos/1820041/pexels-photo-1820041.jpeg?auto=compress&cs=tinysrgb&fit=crop&h=1200&w=800",
"width": 1200,
"height": 627
},
"tiny": {
"src": "https://images.pexels.com/photos/1820041/pexels-photo-1820041.jpeg?auto=compress&cs=tinysrgb&fit=crop&h=1200&w=800",
"width": 280,
"height": 200
},
"blurHash": "|uKV8RayaxayayfQaya|fQ~Wa|j[j[j[fQfkfQfQIAj@f6fkj[fQj[j[fQtSazazf6ayfQfQfQfQWAj[fQa}fQfQa|fQfQWXj[j[ayj[fQfQa|fQWUayfQj[ayjtj[fQfQRkj[ayayfkfRf6j[a|j[ayjsa|fRayfQfQfQ"
},
{
"original": {
"src": "https://images.pexels.com/photos/3363331/pexels-photo-3363331.jpeg",
"width": 3767,
"height": 4709
},
"large2x": {
"src": "https://images.pexels.com/photos/3363331/pexels-photo-3363331.jpeg?auto=compress&cs=tinysrgb&dpr=2&h=650&w=940",
"width": 940,
"height": 650
},
"large": {
"src": "https://images.pexels.com/photos/3363331/pexels-photo-3363331.jpeg?auto=compress&cs=tinysrgb&h=650&w=940",
"width": 940,
"height": 650
},
"portrait": {
"src": "https://images.pexels.com/photos/3363331/pexels-photo-3363331.jpeg?auto=compress&cs=tinysrgb&fit=crop&h=1200&w=800",
"width": 800,
"height": 1200
},
"landscape": {
"src": "https://images.pexels.com/photos/3363331/pexels-photo-3363331.jpeg?auto=compress&cs=tinysrgb&fit=crop&h=1200&w=800",
"width": 1200,
"height": 627
},
"tiny": {
"src": "https://images.pexels.com/photos/3363331/pexels-photo-3363331.jpeg?auto=compress&cs=tinysrgb&fit=crop&h=1200&w=800",
"width": 280,
"height": 200
},
"blurHash": "|kI5PiE1ayRjfkazayazWV~qWCofofWCayj[jtjt.8j[ayazjtj[j[j[js%hs:M{WVoLj@ayaya}M{aet7ofaya}ayj[j[M{WVf6f6bHayfRaya}IUogWBa}fkjZaya|a}M{WBs:j]jtfkj[j[j[ozf5kCWBayoLayfkay"
},
{
"original": {
"src": "https://images.pexels.com/photos/1532771/pexels-photo-1532771.jpeg",
"width": 2500,
"height": 1717
},
"large2x": {
"src": "https://images.pexels.com/photos/1532771/pexels-photo-1532771.jpeg?auto=compress&cs=tinysrgb&dpr=2&h=650&w=940",
"width": 940,
"height": 650
},
"large": {
"src": "https://images.pexels.com/photos/1532771/pexels-photo-1532771.jpeg?auto=compress&cs=tinysrgb&h=650&w=940",
"width": 940,
"height": 650
},
"portrait": {
"src": "https://images.pexels.com/photos/1532771/pexels-photo-1532771.jpeg?auto=compress&cs=tinysrgb&fit=crop&h=1200&w=800",
"width": 800,
"height": 1200
},
"landscape": {
"src": "https://images.pexels.com/photos/1532771/pexels-photo-1532771.jpeg?auto=compress&cs=tinysrgb&fit=crop&h=1200&w=800",
"width": 1200,
"height": 627
},
"tiny": {
"src": "https://images.pexels.com/photos/1532771/pexels-photo-1532771.jpeg?auto=compress&cs=tinysrgb&fit=crop&h=1200&w=800",
"width": 280,
"height": 200
},
"blurHash": "|ZK1w._3RjxbRjs:WVofa}kcROofWBkCj[azfPay5vNejFWXn~WCoJa#j[9vofoeWVofayj[ayf6H;V[o#jYWVjYa#j?bH^+oIM{ofWBofaxj[ay9to$t6WVoeWVj?bHjsS%RjoLj[f6bHj[ayj[wHadWEaebHf5ayj[az"
},
{
"original": {
"src": "https://images.pexels.com/photos/2248523/pexels-photo-2248523.jpeg",
"width": 4000,
"height": 6000
},
"large2x": {
"src": "https://images.pexels.com/photos/2248523/pexels-photo-2248523.jpeg?auto=compress&cs=tinysrgb&dpr=2&h=650&w=940",
"width": 940,
"height": 650
},
"large": {
"src": "https://images.pexels.com/photos/2248523/pexels-photo-2248523.jpeg?auto=compress&cs=tinysrgb&h=650&w=940",
"width": 940,
"height": 650
},
"portrait": {
"src": "https://images.pexels.com/photos/2248523/pexels-photo-2248523.jpeg?auto=compress&cs=tinysrgb&fit=crop&h=1200&w=800",
"width": 800,
"height": 1200
},
"landscape": {
"src": "https://images.pexels.com/photos/2248523/pexels-photo-2248523.jpeg?auto=compress&cs=tinysrgb&fit=crop&h=1200&w=800",
"width": 1200,
"height": 627
},
"tiny": {
"src": "https://images.pexels.com/photos/2248523/pexels-photo-2248523.jpeg?auto=compress&cs=tinysrgb&fit=crop&h=1200&w=800",
"width": 280,
"height": 200
},
"blurHash": "|lG[]4offkayj[fQfRfQjt~qoLj@j[fQfQfQfQfQE2j[jtj[fkfQfQfQfQELfQj[ayfPfQfQfQfQadayayfQfQfPfPfQfQsSfQfQj[fkfQj[fQfQoff6j[ayayfQfQfRfQX9j[ayfQj[fQfQa|fQR*j[fkj[fQfQfQfQfQ"
},
{
"original": {
"src": "https://images.pexels.com/photos/37730/sunset-boat-sea-ship-37730.jpeg",
"width": 2048,
"height": 1365
},
"large2x": {
"src": "https://images.pexels.com/photos/37730/sunset-boat-sea-ship-37730.jpeg?auto=compress&cs=tinysrgb&dpr=2&h=650&w=940",
"width": 940,
"height": 650
},
"large": {
"src": "https://images.pexels.com/photos/37730/sunset-boat-sea-ship-37730.jpeg?auto=compress&cs=tinysrgb&h=650&w=940",
"width": 940,
"height": 650
},
"portrait": {
"src": "https://images.pexels.com/photos/37730/sunset-boat-sea-ship-37730.jpeg?auto=compress&cs=tinysrgb&fit=crop&h=1200&w=800",
"width": 800,
"height": 1200
},
"landscape": {
"src": "https://images.pexels.com/photos/37730/sunset-boat-sea-ship-37730.jpeg?auto=compress&cs=tinysrgb&fit=crop&h=1200&w=800",
"width": 1200,
"height": 627
},
"tiny": {
"src": "https://images.pexels.com/photos/37730/sunset-boat-sea-ship-37730.jpeg?auto=compress&cs=tinysrgb&fit=crop&h=1200&w=800",
"width": 280,
"height": 200
},
"blurHash": "|dOeLY=^EM$%NHjtj@WWjs~TNbs.R+ayj[WVj[ayJVNIs.R+jZWVj[j@WVrtjHWqWCj@WVj[azjtE3f7fkWBfQaya|a}j[JAoyWCazayayfkjta|xXoeWVf6WVjaaza|oLxYoeRkj@ayayjta|jtI@juafa|jsayazj@az"
},
{
"original": {
"src": "https://images.pexels.com/photos/1726310/pexels-photo-1726310.jpeg",
"width": 3968,
"height": 2645
},
"large2x": {
"src": "https://images.pexels.com/photos/1726310/pexels-photo-1726310.jpeg?auto=compress&cs=tinysrgb&dpr=2&h=650&w=940",
"width": 940,
"height": 650
},
"large": {
"src": "https://images.pexels.com/photos/1726310/pexels-photo-1726310.jpeg?auto=compress&cs=tinysrgb&h=650&w=940",
"width": 940,
"height": 650
},
"portrait": {
"src": "https://images.pexels.com/photos/1726310/pexels-photo-1726310.jpeg?auto=compress&cs=tinysrgb&fit=crop&h=1200&w=800",
"width": 800,
"height": 1200
},
"landscape": {
"src": "https://images.pexels.com/photos/1726310/pexels-photo-1726310.jpeg?auto=compress&cs=tinysrgb&fit=crop&h=1200&w=800",
"width": 1200,
"height": 627
},
"tiny": {
"src": "https://images.pexels.com/photos/1726310/pexels-photo-1726310.jpeg?auto=compress&cs=tinysrgb&fit=crop&h=1200&w=800",
"width": 280,
"height": 200
},
"blurHash": "|mJavADNEQJBWUn$s;WBayEiNaWBxas.n$s:oLWBozf5s9xZWDNHS2bbfQs:NGbIays:WVofjZoLj[kBoeaeoMjZWBWVbHsmj[bIR*WBj]a|WBoLa}j[oLWVfkj[oJoLWCj[WBj[WWj@j[j]WVays:WUayofayj[ayayj["
},
{
"original": {
"src": "https://images.pexels.com/photos/1032650/pexels-photo-1032650.jpeg",
"width": 4405,
"height": 6607
},
"large2x": {
"src": "https://images.pexels.com/photos/1032650/pexels-photo-1032650.jpeg?auto=compress&cs=tinysrgb&dpr=2&h=650&w=940",
"width": 940,
"height": 650
},
"large": {
"src": "https://images.pexels.com/photos/1032650/pexels-photo-1032650.jpeg?auto=compress&cs=tinysrgb&h=650&w=940",
"width": 940,
"height": 650
},
"portrait": {
"src": "https://images.pexels.com/photos/1032650/pexels-photo-1032650.jpeg?auto=compress&cs=tinysrgb&fit=crop&h=1200&w=800",
"width": 800,
"height": 1200
},
"landscape": {
"src": "https://images.pexels.com/photos/1032650/pexels-photo-1032650.jpeg?auto=compress&cs=tinysrgb&fit=crop&h=1200&w=800",
"width": 1200,
"height": 627
},
"tiny": {
"src": "https://images.pexels.com/photos/1032650/pexels-photo-1032650.jpeg?auto=compress&cs=tinysrgb&fit=crop&h=1200&w=800",
"width": 280,
"height": 200
},
"blurHash": "|iKv,Fs:E2WBkCofWBe.bHF~bHslj@ayayj[j[f60gjZoykBafaej[bHfPD*aybIazj[j[ayf6fkELWWoLayjua}j[fjf6^gj@jFjZbHfkjZaxbHoyazjZj[a{fPjuj[j@NKjZS#bHjFaybHj]ayaLoLazf6fkfkf6aybH"
},
{
"original": {
"src": "https://images.pexels.com/photos/1404918/pexels-photo-1404918.jpeg",
"width": 3000,
"height": 2000
},
"large2x": {
"src": "https://images.pexels.com/photos/1404918/pexels-photo-1404918.jpeg?auto=compress&cs=tinysrgb&dpr=2&h=650&w=940",
"width": 940,
"height": 650
},
"large": {
"src": "https://images.pexels.com/photos/1404918/pexels-photo-1404918.jpeg?auto=compress&cs=tinysrgb&h=650&w=940",
"width": 940,
"height": 650
},
"portrait": {
"src": "https://images.pexels.com/photos/1404918/pexels-photo-1404918.jpeg?auto=compress&cs=tinysrgb&fit=crop&h=1200&w=800",
"width": 800,
"height": 1200
},
"landscape": {
"src": "https://images.pexels.com/photos/1404918/pexels-photo-1404918.jpeg?auto=compress&cs=tinysrgb&fit=crop&h=1200&w=800",
"width": 1200,
"height": 627
},
"tiny": {
"src": "https://images.pexels.com/photos/1404918/pexels-photo-1404918.jpeg?auto=compress&cs=tinysrgb&fit=crop&h=1200&w=800",
"width": 280,
"height": 200
},
"blurHash": "|RK+}}0zEgJUS$j?bbofozBpEL%Ms:S4RkX9s:RkF{o#smV@xtxGIokCWBWCf6n%WBRj%2RjbHWBShn+aet7V@ofRjkCoeNGt8jFWBS4ogs.WBbHfkjYt7oMNGbIt6oeR*bcWBaet7RjWBoeoLR*WBt7WBofofR*bHoLR*"
},
{
"original": {
"src": "https://images.pexels.com/photos/1249586/pexels-photo-1249586.jpeg",
"width": 3992,
"height": 2190
},
"large2x": {
"src": "https://images.pexels.com/photos/1249586/pexels-photo-1249586.jpeg?auto=compress&cs=tinysrgb&dpr=2&h=650&w=940",
"width": 940,
"height": 650
},
"large": {
"src": "https://images.pexels.com/photos/1249586/pexels-photo-1249586.jpeg?auto=compress&cs=tinysrgb&h=650&w=940",
"width": 940,
"height": 650
},
"portrait": {
"src": "https://images.pexels.com/photos/1249586/pexels-photo-1249586.jpeg?auto=compress&cs=tinysrgb&fit=crop&h=1200&w=800",
"width": 800,
"height": 1200
},
"landscape": {
"src": "https://images.pexels.com/photos/1249586/pexels-photo-1249586.jpeg?auto=compress&cs=tinysrgb&fit=crop&h=1200&w=800",
"width": 1200,
"height": 627
},
"tiny": {
"src": "https://images.pexels.com/photos/1249586/pexels-photo-1249586.jpeg?auto=compress&cs=tinysrgb&fit=crop&h=1200&w=800",
"width": 280,
"height": 200
},
"blurHash": "|zMGYJxabHj[j]ayfQj@fP1Mofj[WBj[ayf6fPf6IoX8jsazaxj[fPfQfki]Rjayofaej[fQfkj[enV?WVj]j]ayfQj[ayozjYWBWVkCayj[fQf6f+ogaeaeayj[j[f6fkj@ogj[ayaej[fkayj[f6jZkCj[ayf6fQfRay"
},
{
"original": {
"src": "https://images.pexels.com/photos/1482193/pexels-photo-1482193.jpeg",
"width": 6016,
"height": 4000
},
"large2x": {
"src": "https://images.pexels.com/photos/1482193/pexels-photo-1482193.jpeg?auto=compress&cs=tinysrgb&dpr=2&h=650&w=940",
"width": 940,
"height": 650
},
"large": {
"src": "https://images.pexels.com/photos/1482193/pexels-photo-1482193.jpeg?auto=compress&cs=tinysrgb&h=650&w=940",
"width": 940,
"height": 650
},
"portrait": {
"src": "https://images.pexels.com/photos/1482193/pexels-photo-1482193.jpeg?auto=compress&cs=tinysrgb&fit=crop&h=1200&w=800",
"width": 800,
"height": 1200
},
"landscape": {
"src": "https://images.pexels.com/photos/1482193/pexels-photo-1482193.jpeg?auto=compress&cs=tinysrgb&fit=crop&h=1200&w=800",
"width": 1200,
"height": 627
},
"tiny": {
"src": "https://images.pexels.com/photos/1482193/pexels-photo-1482193.jpeg?auto=compress&cs=tinysrgb&fit=crop&h=1200&w=800",
"width": 280,
"height": 200
},
"blurHash": "|lDBHNRQj[ayfka|ayfkf6uPayjsj[ayjtfkfQfQ5qs:j[jtfQjtj[ayj[E3oLaza}j[fkjtfkfQ+[WBa|a}jZaza|j@f6-7ayfQayj[aya|f6fQS$oLjsfRjsa|f6a|fQEhoLjsjtayj[jtfQfPjFWVbHa}fkjsfRjtfQ"
},
{
"original": {
"src": "https://images.pexels.com/photos/175773/pexels-photo-175773.jpeg",
"width": 5616,
"height": 3744
},
"large2x": {
"src": "https://images.pexels.com/photos/175773/pexels-photo-175773.jpeg?auto=compress&cs=tinysrgb&dpr=2&h=650&w=940",
"width": 940,
"height": 650
},
"large": {
"src": "https://images.pexels.com/photos/175773/pexels-photo-175773.jpeg?auto=compress&cs=tinysrgb&h=650&w=940",
"width": 940,
"height": 650
},
"portrait": {
"src": "https://images.pexels.com/photos/175773/pexels-photo-175773.jpeg?auto=compress&cs=tinysrgb&fit=crop&h=1200&w=800",
"width": 800,
"height": 1200
},
"landscape": {
"src": "https://images.pexels.com/photos/175773/pexels-photo-175773.jpeg?auto=compress&cs=tinysrgb&fit=crop&h=1200&w=800",
"width": 1200,
"height": 627
},
"tiny": {
"src": "https://images.pexels.com/photos/175773/pexels-photo-175773.jpeg?auto=compress&cs=tinysrgb&fit=crop&h=1200&w=800",
"width": 280,
"height": 200
},
"blurHash": "|bEEAn%gV@WXozayj[oeoe_Nw[V@WBayj?jZj[WCt6IVR-jZjZayj@ayfRMxM{R+WCofWCfka{jsx]tRV@WBbHaeayofjts,xZt7WBj?bHj[WCa|WBt6s.ofaya#a{ayayM|o#oekCoeWBa}fkfQM|tQoyjZofayayfRf6"
},
{
"original": {
"src": "https://images.pexels.com/photos/1683724/pexels-photo-1683724.jpeg",
"width": 2000,
"height": 2000
},
"large2x": {
"src": "https://images.pexels.com/photos/1683724/pexels-photo-1683724.jpeg?auto=compress&cs=tinysrgb&dpr=2&h=650&w=940",
"width": 940,
"height": 650
},
"large": {
"src": "https://images.pexels.com/photos/1683724/pexels-photo-1683724.jpeg?auto=compress&cs=tinysrgb&h=650&w=940",
"width": 940,
"height": 650
},
"portrait": {
"src": "https://images.pexels.com/photos/1683724/pexels-photo-1683724.jpeg?auto=compress&cs=tinysrgb&fit=crop&h=1200&w=800",
"width": 800,
"height": 1200
},
"landscape": {
"src": "https://images.pexels.com/photos/1683724/pexels-photo-1683724.jpeg?auto=compress&cs=tinysrgb&fit=crop&h=1200&w=800",
"width": 1200,
"height": 627
},
"tiny": {
"src": "https://images.pexels.com/photos/1683724/pexels-photo-1683724.jpeg?auto=compress&cs=tinysrgb&fit=crop&h=1200&w=800",
"width": 280,
"height": 200
},
"blurHash": "|ABg9_E.xvxVxYtR-oW?e-ThNL-.D*WCWXs:WBayER_3NeR*%0e-NKs+j]9u%MjZ?GE3xZt6ogoznNIWIrs.NGRkM{RkWBEORP$KIq%2M_WAt6oeMxIVIVR.%1NJozRjflMxIUM{xtE2ayV@NGoze-n#Rk%1Rjxuozofae"
},
{
"original": {
"src": "https://images.pexels.com/photos/1320684/pexels-photo-1320684.jpeg",
"width": 4000,
"height": 3000
},
"large2x": {
"src": "https://images.pexels.com/photos/1320684/pexels-photo-1320684.jpeg?auto=compress&cs=tinysrgb&dpr=2&h=650&w=940",
"width": 940,
"height": 650
},
"large": {
"src": "https://images.pexels.com/photos/1320684/pexels-photo-1320684.jpeg?auto=compress&cs=tinysrgb&h=650&w=940",
"width": 940,
"height": 650
},
"portrait": {
"src": "https://images.pexels.com/photos/1320684/pexels-photo-1320684.jpeg?auto=compress&cs=tinysrgb&fit=crop&h=1200&w=800",
"width": 800,
"height": 1200
},
"landscape": {
"src": "https://images.pexels.com/photos/1320684/pexels-photo-1320684.jpeg?auto=compress&cs=tinysrgb&fit=crop&h=1200&w=800",
"width": 1200,
"height": 627
},
"tiny": {
"src": "https://images.pexels.com/photos/1320684/pexels-photo-1320684.jpeg?auto=compress&cs=tinysrgb&fit=crop&h=1200&w=800",
"width": 280,
"height": 200
},
"blurHash": "|A9AE5~J%3%}9YaexbI.%2K+P8tQyDnOs;o|V@kD01Mxi^Oq-pozRj$*NZv#xHQ-IURiM{V@s.XSv$RkV@rrNGV@nPM{kqSySdtQxtyDxaozX8jGs:s:jGS#aeogf,njtRt8iwkCo2RjR+aeX6oLMxRQVtnispjZbbWBV@"
},
{
"original": {
"src": "https://images.pexels.com/photos/2422914/pexels-photo-2422914.jpeg",
"width": 3648,
"height": 5472
},
"large2x": {
"src": "https://images.pexels.com/photos/2422914/pexels-photo-2422914.jpeg?auto=compress&cs=tinysrgb&dpr=2&h=650&w=940",
"width": 940,
"height": 650
},
"large": {
"src": "https://images.pexels.com/photos/2422914/pexels-photo-2422914.jpeg?auto=compress&cs=tinysrgb&h=650&w=940",
"width": 940,
"height": 650
},
"portrait": {
"src": "https://images.pexels.com/photos/2422914/pexels-photo-2422914.jpeg?auto=compress&cs=tinysrgb&fit=crop&h=1200&w=800",
"width": 800,
"height": 1200
},
"landscape": {
"src": "https://images.pexels.com/photos/2422914/pexels-photo-2422914.jpeg?auto=compress&cs=tinysrgb&fit=crop&h=1200&w=800",
"width": 1200,
"height": 627
},
"tiny": {
"src": "https://images.pexels.com/photos/2422914/pexels-photo-2422914.jpeg?auto=compress&cs=tinysrgb&fit=crop&h=1200&w=800",
"width": 280,
"height": 200
},
"blurHash": "|Z8hqNs+ayjsayf6j[j@j[DNR+j[a|j[fkfQayay%gofayfkfkayf6j[fPM{ayjtfQayfkfkfQj[t7j[fkfQj[j[fQfQf6WBayf6fQayayayayfkoefQfjayfPfRj[j[fQayfkfQj[fkj[fRaya|j[fQfjfRj[j[f6f6j["
},
{
"original": {
"src": "https://images.pexels.com/photos/2127969/pexels-photo-2127969.jpeg",
"width": 2598,
"height": 2047
},
"large2x": {
"src": "https://images.pexels.com/photos/2127969/pexels-photo-2127969.jpeg?auto=compress&cs=tinysrgb&dpr=2&h=650&w=940",
"width": 940,
"height": 650
},
"large": {
"src": "https://images.pexels.com/photos/2127969/pexels-photo-2127969.jpeg?auto=compress&cs=tinysrgb&h=650&w=940",
"width": 940,
"height": 650
},
"portrait": {
"src": "https://images.pexels.com/photos/2127969/pexels-photo-2127969.jpeg?auto=compress&cs=tinysrgb&fit=crop&h=1200&w=800",
"width": 800,
"height": 1200
},
"landscape": {
"src": "https://images.pexels.com/photos/2127969/pexels-photo-2127969.jpeg?auto=compress&cs=tinysrgb&fit=crop&h=1200&w=800",
"width": 1200,
"height": 627
},
"tiny": {
"src": "https://images.pexels.com/photos/2127969/pexels-photo-2127969.jpeg?auto=compress&cs=tinysrgb&fit=crop&h=1200&w=800",
"width": 280,
"height": 200
},
"blurHash": "|E6+*6?wv~o2s:ofjtkCj]=}-=x]ozozogj]e.j[+{%No}kCkCjZe.ayay%$tSWBROV@aeaebcayx^oLR4RPg3kCbbadfkt8i^ROk=kCjbaeaekCn3ogpJjFeTjZaef+aet7o#Z~VYkWkCkWayaytRoLaKkqkWkCaeadbI"
},
{
"original": {
"src": "https://images.pexels.com/photos/1054391/pexels-photo-1054391.jpeg",
"width": 2992,
"height": 3992
},
"large2x": {
"src": "https://images.pexels.com/photos/1054391/pexels-photo-1054391.jpeg?auto=compress&cs=tinysrgb&dpr=2&h=650&w=940",
"width": 940,
"height": 650
},
"large": {
"src": "https://images.pexels.com/photos/1054391/pexels-photo-1054391.jpeg?auto=compress&cs=tinysrgb&h=650&w=940",
"width": 940,
"height": 650
},
"portrait": {
"src": "https://images.pexels.com/photos/1054391/pexels-photo-1054391.jpeg?auto=compress&cs=tinysrgb&fit=crop&h=1200&w=800",
"width": 800,
"height": 1200
},
"landscape": {
"src": "https://images.pexels.com/photos/1054391/pexels-photo-1054391.jpeg?auto=compress&cs=tinysrgb&fit=crop&h=1200&w=800",
"width": 1200,
"height": 627
},
"tiny": {
"src": "https://images.pexels.com/photos/1054391/pexels-photo-1054391.jpeg?auto=compress&cs=tinysrgb&fit=crop&h=1200&w=800",
"width": 280,
"height": 200
},
"blurHash": "|G7VWIt7ozf+a{WBayoLj]M{V@WAj@axj]fkfkay8^WBjXkCofoMj]axj]s7oft8V@fRWUWBayjt%NoeWBayaekCbHoeayT1WXWAogj[axoffkf6M{RjoLfRj[azf6azazsln#j]j]aej]axaxkCn~ozWBayj[jtfQj[jt"
},
{
"original": {
"src": "https://images.pexels.com/photos/355328/pexels-photo-355328.jpeg",
"width": 4335,
"height": 2890
},
"large2x": {
"src": "https://images.pexels.com/photos/355328/pexels-photo-355328.jpeg?auto=compress&cs=tinysrgb&dpr=2&h=650&w=940",
"width": 940,
"height": 650
},
"large": {
"src": "https://images.pexels.com/photos/355328/pexels-photo-355328.jpeg?auto=compress&cs=tinysrgb&h=650&w=940",
"width": 940,
"height": 650
},
"portrait": {
"src": "https://images.pexels.com/photos/355328/pexels-photo-355328.jpeg?auto=compress&cs=tinysrgb&fit=crop&h=1200&w=800",
"width": 800,
"height": 1200
},
"landscape": {
"src": "https://images.pexels.com/photos/355328/pexels-photo-355328.jpeg?auto=compress&cs=tinysrgb&fit=crop&h=1200&w=800",
"width": 1200,
"height": 627
},
"tiny": {
"src": "https://images.pexels.com/photos/355328/pexels-photo-355328.jpeg?auto=compress&cs=tinysrgb&fit=crop&h=1200&w=800",
"width": 280,
"height": 200
},
"blurHash": "|NI=iXIUs;j[Rja{fkayoL0.xtt7ayayfkayj[axwis.NFofofofjaj[j[-=RQM|aeofayjZayay%M%2xuaya}WBj[j[j[M_fit7bFWBj[bHWBjtkWM{R*ayayj[ayfRWBxtWURjogofofayayj]D%oLoLaxofWBofofj@"
},
{
"original": {
"src": "https://images.pexels.com/photos/691858/pexels-photo-691858.jpeg",
"width": 6000,
"height": 4000
},
"large2x": {
"src": "https://images.pexels.com/photos/691858/pexels-photo-691858.jpeg?auto=compress&cs=tinysrgb&dpr=2&h=650&w=940",
"width": 940,
"height": 650
},
"large": {
"src": "https://images.pexels.com/photos/691858/pexels-photo-691858.jpeg?auto=compress&cs=tinysrgb&h=650&w=940",
"width": 940,
"height": 650
},
"portrait": {
"src": "https://images.pexels.com/photos/691858/pexels-photo-691858.jpeg?auto=compress&cs=tinysrgb&fit=crop&h=1200&w=800",
"width": 800,
"height": 1200
},
"landscape": {
"src": "https://images.pexels.com/photos/691858/pexels-photo-691858.jpeg?auto=compress&cs=tinysrgb&fit=crop&h=1200&w=800",
"width": 1200,
"height": 627
},
"tiny": {
"src": "https://images.pexels.com/photos/691858/pexels-photo-691858.jpeg?auto=compress&cs=tinysrgb&fit=crop&h=1200&w=800",
"width": 280,
"height": 200
},
"blurHash": "|g7y#HWAj@fPfPf6f6fRj@*0WBj[fkf6fQfQj[fQtRayjtfQfRfQf6j[fQoffRf6j@fQf6fQj@fQj[a}fQfjfkf6fRfQfRj[ayf6fjfQfQfRf7fQkCf6f6f6fQfRfQfQfQkCfkfkfRayfQf6fQfQjsf6ayfkfRfPfQfQfQ"
},
{
"original": {
"src": "https://images.pexels.com/photos/636353/pexels-photo-636353.jpeg",
"width": 4000,
"height": 3000
},
"large2x": {
"src": "https://images.pexels.com/photos/636353/pexels-photo-636353.jpeg?auto=compress&cs=tinysrgb&dpr=2&h=650&w=940",
"width": 940,
"height": 650
},
"large": {
"src": "https://images.pexels.com/photos/636353/pexels-photo-636353.jpeg?auto=compress&cs=tinysrgb&h=650&w=940",
"width": 940,
"height": 650
},
"portrait": {
"src": "https://images.pexels.com/photos/636353/pexels-photo-636353.jpeg?auto=compress&cs=tinysrgb&fit=crop&h=1200&w=800",
"width": 800,
"height": 1200
},
"landscape": {
"src": "https://images.pexels.com/photos/636353/pexels-photo-636353.jpeg?auto=compress&cs=tinysrgb&fit=crop&h=1200&w=800",
"width": 1200,
"height": 627
},
"tiny": {
"src": "https://images.pexels.com/photos/636353/pexels-photo-636353.jpeg?auto=compress&cs=tinysrgb&fit=crop&h=1200&w=800",
"width": 280,
"height": 200
},
"blurHash": "|t8?::V@fPf6fQfQfQfQfQ*0WCfQfQfQfQfQfQfQt2a}fQfQfQfQfQfQfQofa|fQfQfQfQfQfQfQoLazfQfQfQfQfQfQfQkCazfQfQfQfQfQfQfQj?azfQfQfQfQfQfQfQj[fQfQfQfQfQfQfQfQj@fQfQfQfQfQfQfQfQ"
},
{
"original": {
"src": "https://images.pexels.com/photos/154246/pexels-photo-154246.jpeg",
"width": 5472,
"height": 3648
},
"large2x": {
"src": "https://images.pexels.com/photos/154246/pexels-photo-154246.jpeg?auto=compress&cs=tinysrgb&dpr=2&h=650&w=940",
"width": 940,
"height": 650
},
"large": {
"src": "https://images.pexels.com/photos/154246/pexels-photo-154246.jpeg?auto=compress&cs=tinysrgb&h=650&w=940",
"width": 940,
"height": 650
},
"portrait": {
"src": "https://images.pexels.com/photos/154246/pexels-photo-154246.jpeg?auto=compress&cs=tinysrgb&fit=crop&h=1200&w=800",
"width": 800,
"height": 1200
},
"landscape": {
"src": "https://images.pexels.com/photos/154246/pexels-photo-154246.jpeg?auto=compress&cs=tinysrgb&fit=crop&h=1200&w=800",
"width": 1200,
"height": 627
},
"tiny": {
"src": "https://images.pexels.com/photos/154246/pexels-photo-154246.jpeg?auto=compress&cs=tinysrgb&fit=crop&h=1200&w=800",
"width": 280,
"height": 200
},
"blurHash": "|wLq;Gj[ayj[ayj[fQj[fQ~qfkfQfQfQfQfQfQfQRPayfQfQfQfQfQfQfQoffQfQfQfQfQfQfQfQaefQfQfQfQfQfQfQfQofazfQfQfQfQfQfQfQfRfQfQfQfQfQfQfQfQazfPfQfQfQfQfQfQfQfPfQfQfQfQfQfQfQfQ"
},
{
"original": {
"src": "https://images.pexels.com/photos/2524874/pexels-photo-2524874.jpeg",
"width": 2400,
"height": 3600
},
"large2x": {
"src": "https://images.pexels.com/photos/2524874/pexels-photo-2524874.jpeg?auto=compress&cs=tinysrgb&dpr=2&h=650&w=940",
"width": 940,
"height": 650
},
"large": {
"src": "https://images.pexels.com/photos/2524874/pexels-photo-2524874.jpeg?auto=compress&cs=tinysrgb&h=650&w=940",
"width": 940,
"height": 650
},
"portrait": {
"src": "https://images.pexels.com/photos/2524874/pexels-photo-2524874.jpeg?auto=compress&cs=tinysrgb&fit=crop&h=1200&w=800",
"width": 800,
"height": 1200
},
"landscape": {
"src": "https://images.pexels.com/photos/2524874/pexels-photo-2524874.jpeg?auto=compress&cs=tinysrgb&fit=crop&h=1200&w=800",
"width": 1200,
"height": 627
},
"tiny": {
"src": "https://images.pexels.com/photos/2524874/pexels-photo-2524874.jpeg?auto=compress&cs=tinysrgb&fit=crop&h=1200&w=800",
"width": 280,
"height": 200
},
"blurHash": "|G8q{V01$xs:S5V?t7WXV@u5RkrqkCWYjYoLf+V@tSWBV@ozayaekCayayWEofaekCWBofa}WBofRkoeoLWCaxofWVaeofRjofayWVjsofWVWBt7R*oeaybHayofayjZj[a}jsf6a}j[ayfkaxofbHj?aybHj[aykCaxfk"
},
{
"original": {
"src": "https://images.pexels.com/photos/88517/pexels-photo-88517.jpeg",
"width": 3456,
"height": 5184
},
"large2x": {
"src": "https://images.pexels.com/photos/88517/pexels-photo-88517.jpeg?auto=compress&cs=tinysrgb&dpr=2&h=650&w=940",
"width": 940,
"height": 650
},
"large": {
"src": "https://images.pexels.com/photos/88517/pexels-photo-88517.jpeg?auto=compress&cs=tinysrgb&h=650&w=940",
"width": 940,
"height": 650
},
"portrait": {
"src": "https://images.pexels.com/photos/88517/pexels-photo-88517.jpeg?auto=compress&cs=tinysrgb&fit=crop&h=1200&w=800",
"width": 800,
"height": 1200
},
"landscape": {
"src": "https://images.pexels.com/photos/88517/pexels-photo-88517.jpeg?auto=compress&cs=tinysrgb&fit=crop&h=1200&w=800",
"width": 1200,
"height": 627
},
"tiny": {
"src": "https://images.pexels.com/photos/88517/pexels-photo-88517.jpeg?auto=compress&cs=tinysrgb&fit=crop&h=1200&w=800",
"width": 280,
"height": 200
},
"blurHash": "|ZC[nBtRaej[fkj[ayfkfj.ToKfQj[fQfkfQfQfQ4oWBj[ayf6fQj[fQfQ9~bHf6azfQazfQfQfQV@ayf7fjfQa|azfQfQxFbHj@j[fQfQfQfQfQxZfkfQfQfQfQfQfQfQa}f6f7ayfQfQfQfQfQNHfQfQfQfQfQfQfQfQ"
},
{
"original": {
"src": "https://images.pexels.com/photos/36487/above-adventure-aerial-air.jpg",
"width": 1920,
"height": 1307
},
"large2x": {
"src": "https://images.pexels.com/photos/36487/above-adventure-aerial-air.jpg?auto=compress&cs=tinysrgb&dpr=2&h=650&w=940",
"width": 940,
"height": 650
},
"large": {
"src": "https://images.pexels.com/photos/36487/above-adventure-aerial-air.jpg?auto=compress&cs=tinysrgb&h=650&w=940",
"width": 940,
"height": 650
},
"portrait": {
"src": "https://images.pexels.com/photos/36487/above-adventure-aerial-air.jpg?auto=compress&cs=tinysrgb&fit=crop&h=1200&w=800",
"width": 800,
"height": 1200
},
"landscape": {
"src": "https://images.pexels.com/photos/36487/above-adventure-aerial-air.jpg?auto=compress&cs=tinysrgb&fit=crop&h=1200&w=800",
"width": 1200,
"height": 627
},
"tiny": {
"src": "https://images.pexels.com/photos/36487/above-adventure-aerial-air.jpg?auto=compress&cs=tinysrgb&fit=crop&h=1200&w=800",
"width": 280,
"height": 200
}
}
]
